Workbook
Name Агенты: Каналы!$K$4:$K$5
Name ГК: ЛБ!$I$22
Name Групп.пенсия: ЛБ!$M$22
Name ДМС: ЛБ!$R$22
Name ДМС_СИВ: ЛБ!$S$22
Name Индив.пенсия: ЛБ!$N$22
Name ИСЖ_СИВ: ЛБ!$Q$22
Name ИСЖ_Уралсиб: ЛБ!$AB$22
Name КорпЖ: ЛБ!$T$22
Name КорпНС: ЛБ!$U$22
Name Корпораты: Каналы!$L$4
Name КСЖ: ЛБ!$V$22
Name КСЖ_СИВ: ЛБ!$W$22
Name КСЖ_Уралсиб: ЛБ!$AD$22:$AD$23
Name Мульти: Каналы!$M$4
Name НовыеТП: Табл.НовыеТП[]
Name Новый: ЛБ!$J$4:$J$7
Name НП: ЛБ!$J$22
Name НС: ЛБ!$X$22:$X$23
Name НС_СИВ: ЛБ!$Y$22
Name НСЖ: ЛБ!$O$22:$O$28
Name НСЖ_КБ: ЛБ!$L$22
Name НСЖ_новый: ЛБ!$K$22
Name НСЖ_СИВ: ЛБ!$P$22:$P$28
Name НСЖ_СИВ_ДМС: ЛБ!$Z$22:$Z$28
Name НСЖ_СИВ_НС: ЛБ!$AA$22:$AA$28
Name НСЖ_Уралсиб: ЛБ!$AC$22:$AC$24
Name Портфель: ЛБ!$H$4:$H$6
Name Прочее_Уралсиб: ЛБ!$AE$22
Name Регион: Регионы!$B$2:$B$91
Name Розница: Каналы!$I$4:$I$7
Name СКБСЖ: ЛБ!$K$4:$K$18
Name Уралсиб: ЛБ!$L$4:$L$7
Name Уралсиб_: Каналы!$J$4

Sheet Дюрация
X1: изначально = факту, но с возможностью корректировки
F2: куб | G2: куб | H2: куб | I2: куб | J2: куб | K2: куб | L2: расчет | M2: расчет | N2: расчет | O2: расчет | P2: расчет | Q2: расчет | R2: расчет | S2: расчет | T2: расчет | U2: расчет | V2: расчет | W2: расчет | X2: ввод | Y2: ввод | Z2: ввод | AA2: ввод | AB2: ввод | AC2: ввод
F3: Дюрация факт 2025 | R3: Дюрация план 2026
F4: Дюрация факт 2025 | L4: Дюрация факт 2025, структура,% | R4: Дюрация факт 2025 | X4: Дюрация факт 2025, структура,%
B5: Компания | C5: подканал | D5: ЛБ | E5: Продукт | F5: < 1 г | G5: 1-3 | H5: 3-5 | I5: 5-10 | J5: 10+ | K5: итого | L5: < 1 г | M5: 1-3 | N5: 3-5 | O5: 5-10 | P5: 10+ | Q5: итого | R5: < 1 г | S5: 1-3 | T5: 3-5 | U5: 5-10 | V5: 10+ | W5: итого | X5: < 1 г | Y5: 1-3 | Z5: 3-5 | AA5: 5-10 | AB5: 10+ | AC5: итого
B6: СКБСЖ | C6: WM | D6: НСЖ | E6: НП | F6: 100000 | G6: 150000 | H6: 230000 | I6: 450000 | J6: 562000 | K6: =SUM(F6:J6) -> 1492000 | L6: =F6/$K$6 -> 0.067024129 | M6: =G6/$K$6 -> 0.10053619 | N6: =H6/$K$6 -> 0.1541555 | O6: =I6/$K$6 -> 0.30160858 | P6: =J6/$K$6 -> 0.3766756 | Q6: =K6/$K$6 -> 1 | R6: =$W$6*X6 -> 100536.19 | S6: =$W$6*Y6 -> 150804.29 | T6: =$W$6*Z6 -> 231233.24 | U6: =$W$6*AA6 -> 452412.87 | V6: =$W$6*AB6 -> 565013.4 | W6: 1500000 | X6: 0.067024129 | Y6: 0.10053619 | Z6: 0.1541555 | AA6: 0.30160858 | AB6: 0.3766756 | AC6: =SUM(X6:AB6) -> 1
K7: =SUM(F7:J7) -> 0 | Q7: =SUM(L7:P7) -> 0 | W7: =SUM(R7:V7) -> 0 | AC7: =SUM(X7:AB7) -> 0
K8: =SUM(F8:J8) -> 0 | Q8: =SUM(L8:P8) -> 0 | W8: =SUM(R8:V8) -> 0 | AC8: =SUM(X8:AB8) -> 0
K9: =SUM(F9:J9) -> 0 | Q9: =SUM(L9:P9) -> 0 | W9: =SUM(R9:V9) -> 0 | AC9: =SUM(X9:AB9) -> 0
K10: =SUM(F10:J10) -> 0 | Q10: =SUM(L10:P10) -> 0 | W10: =SUM(R10:V10) -> 0 | AC10: =SUM(X10:AB10) -> 0
K11: =SUM(F11:J11) -> 0 | Q11: =SUM(L11:P11) -> 0 | W11: =SUM(R11:V11) -> 0 | AC11: =SUM(X11:AB11) -> 0
K12: =SUM(F12:J12) -> 0 | Q12: =SUM(L12:P12) -> 0 | W12: =SUM(R12:V12) -> 0 | AC12: =SUM(X12:AB12) -> 0
K13: =SUM(F13:J13) -> 0 | Q13: =SUM(L13:P13) -> 0 | W13: =SUM(R13:V13) -> 0 | AC13: =SUM(X13:AB13) -> 0
K14: =SUM(F14:J14) -> 0 | Q14: =SUM(L14:P14) -> 0 | W14: =SUM(R14:V14) -> 0 | AC14: =SUM(X14:AB14) -> 0
K15: =SUM(F15:J15) -> 0 | Q15: =SUM(L15:P15) -> 0 | W15: =SUM(R15:V15) -> 0 | AC15: =SUM(X15:AB15) -> 0
K16: =SUM(F16:J16) -> 0 | Q16: =SUM(L16:P16) -> 0 | W16: =SUM(R16:V16) -> 0 | AC16: =SUM(X16:AB16) -> 0
K17: =SUM(F17:J17) -> 0 | Q17: =SUM(L17:P17) -> 0 | W17: =SUM(R17:V17) -> 0 | AC17: =SUM(X17:AB17) -> 0
K18: =SUM(F18:J18) -> 0 | Q18: =SUM(L18:P18) -> 0 | W18: =SUM(R18:V18) -> 0 | AC18: =SUM(X18:AB18) -> 0
... K33: =SUM(F33:J33) -> 0 | Q33: =SUM(L33:P33) -> 0 | W33: =SUM(R33:V33) -> 0 | AC33: =SUM(X33:AB33) -> 0

Sheet ФОРМА СКБСЖ
B1: ПЛАН ПРОДАЖ НА 2026-2028 гг
B2: выбор из списка | C2: формула | D2: выбор из списка | E2: формула | F2: выбор из списка | G2: выбор из списка | H2: формула | I2: выбор из списка | J2: формула | K2: выбор из списка | L2: выбор из списка | M2: выбор из списка | N2: выбор из списка | O2: выгрузка | P2: выгрузка | Q2: выгрузка | R2: выгрузка | S2: выгрузка | T2: выгрузка | U2: выгрузка | V2: выгрузка | W2: выгрузка | X2: ввод | Y2: ввод | Z2: ввод | AA2: расчет | AB2: ввод | AC2: ввод | AD2: ввод | AE2: ввод | AF2: ввод | AG2: ввод | AH2: ввод | AI2: ввод | AJ2: ввод | AK2: ввод | AL2: ввод | AM2: ввод | AN2: расчет | AO2: ввод | AP2: ввод | AQ2: ввод | AR2: ввод | AS2: ввод | AT2: ввод | AU2: ввод | AV2: ввод | AX2: Справочно
N3: ПРОМЕЖУТОЧН.ИТОГ | O3: =SUBTOTAL(9,O6:O161) -> 3.5992846e+09 | P3: =SUBTOTAL(9,P6:P161) -> 4.9361912e+09 | Q3: =SUBTOTAL(9,Q6:Q161) -> 7.4710875e+09 | R3: =SUBTOTAL(9,R6:R161) -> 2.5382695e+09 | S3: =SUBTOTAL(9,S6:S161) -> 3.0460406e+09 | T3: =SUBTOTAL(9,T6:T161) -> 3.1034584e+09 | U3: =SUBTOTAL(9,U6:U161) -> 3.4191617e+09 | V3: =SUBTOTAL(9,V6:V161) -> 1.5918354e+09 | ... AP3: =SUBTOTAL(9,AP6:AP161) -> 0 | AX3: =SUBTOTAL(9,AX6:AX161) -> 1.7488223e+09 | AY3: =SUBTOTAL(9,AY6:AY161) -> 1.3782305e+09 | AZ3: =SUBTOTAL(9,AZ6:AZ161) -> 1.4515232e+09 | BA3: =SUBTOTAL(9,BA6:BA161) -> 1.2856077e+09 | BB3: =SUBTOTAL(9,BB6:BB161) -> 1.2535721e+09 | BC3: =SUBTOTAL(9,BC6:BC161) -> 1.5559406e+09
B4: 1 | C4: 2 | D4: 3 | E4: 4 | F4: 5 | G4: 6 | H4: 7 | I4: 8 | J4: 9 | K4: 10 | L4: 11 | M4: 12 | N4: 13 | O4: Премия факт 9 мес 2025 | X4: Премия прогноз 4 кв 2025 | AA4: Итого | AB4: Премия план 2026 | AO4: Премия план 2027-2028 | AQ4: %КВ | AU4: Дополнительные поля | AX4: Премия прогноз 4 кв 2025 (1 версия) | BA4: Дельта прогноз 4кв 2025 (было / стало)
A5: ключ | B5: Компания | C5: Канал | D5: Подканал | E5: Подканал (код) | F5: Регион | G5: Новые ТП | H5: L/NL | I5: Портфель | J5: Сегмент | K5: ЛБ | L5: Продукт | M5: Периодичность | N5: Новый бизнес/ Пролонгация | O5: 45658 | P5: 45689 | Q5: 45717 | R5: 45748 | S5: 45778 | T5: 45809 | U5: 45839 | V5: 45870 | W5: 45901 | X5: 45931 | Y5: 45962 | Z5: 45992 | AA5: 2025 | AB5: 46023 | AC5: 46054 | AD5: 46082 | AE5: 46113 | AF5: 46143 | AG5: 46174 | AH5: 46204 | AI5: 46235 | AJ5: 46266 | AK5: 46296 | AL5: 46327 | AM5: 46357 | AN5: 2026 | AO5: 2027 | AP5: 2028 | AQ5: %КВ 2025 | AR5: %КВ 2026 | AS5: %КВ 2027 | AT5: %КВ 2028 | AU5: Ответственный (ФИО) | AV5: Пояснения к плану | AW5: коммент к корректировке прогноза 4кв25 | AX5: 45931 | AY5: 45962 | AZ5: 45992 | BA5: 45931 | BB5: 45962 | BC5: 45992
A6: =CONCATENATE(B6,C6,D6,E6,F6,G6,H6,I6,J6,K6,L6,M6,N6) -> СКБСЖРозницаWMЛайфНовыйГКГибкий курсЕдиновременнаяНовый | B6: СКБСЖ | C6: =IFERROR(VLOOKUP(D6,Каналы!$B:$C,2,0),"") -> Розница | D6: WM | H6: Лайф | I6: Новый | K6: ГК | L6: Гибкий курс | M6: Единовременная | N6: Новый | O6: 2.6573514e+08 | P6: 208306422 | Q6: 2.1587187e+08 | R6: 408691916 | S6: 183113109 | T6: 2.7109713e+08 | U6: 272935614 | V6: 185626860 | W6: 2.6235146e+08 | X6: 270000000 | Y6: 220000000 | Z6: 220000000 | AA6: =SUM(O6:Z6) -> 2.9837295e+09 | AB6: 150000000 | AC6: 150000000 | AD6: 200000000 | AE6: 200000000 | AF6: 150000000 | AG6: 200000000 | AH6: 200000000 | AI6: 200000000 | AJ6: 300000000 | AK6: 350000000 | AL6: 350000000 | AM6: 350000000 | AN6: =SUM(AB6:AM6) -> 2800000000 | AW6: ок | AX6: 270000000 | AY6: 220000000 | AZ6: 220000000 | BA6: =X6-AX6 -> 0 | BB6: =Y6-AY6 -> 0 | BC6: =Z6-AZ6 -> 0
A7: =CONCATENATE(B7,C7,D7,E7,F7,G7,H7,I7,J7,K7,L7,M7,N7) -> СКБСЖРозницаWMЛайфНовыйНПНПЕдиновременнаяНовый | B7: СКБСЖ | C7: =IFERROR(VLOOKUP(D7,Каналы!$B:$C,2,0),"") -> Розница | D7: WM | H7: Лайф | I7: Новый | K7: НП | L7: НП | M7: Единовременная | N7: Новый | O7: 2.6297489e+09 | P7: 3941211255 | Q7: 6.3700647e+09 | R7: 1.0261065e+09 | S7: 1.9611793e+09 | T7: 1954316259 | U7: 2190823168 | V7: 328435677 | W7: 583395118 | X7: 1200000000 | Y7: 1200000000 | Z7: 1500000000 | AA7: =SUM(O7:Z7) -> 2.4885281e+10 | AB7: 200000000 | AC7: 350000000 | AD7: 350000000 | AE7: 350000000 | AF7: 300000000 | AG7: 350000000 | AH7: 500000000 | AI7: 600000000 | AJ7: 600000000 | AK7: 700000000 | AL7: 700000000 | AM7: 700000000 | AN7: =SUM(AB7:AM7) -> 5700000000 | AW7: увеличено (факт окт 1,2 млрд) | AX7: 393000000 | AY7: 350000000 | AZ7: 350000000 | BA7: =X7-AX7 -> 807000000 | BB7: =Y7-AY7 -> 850000000 | BC7: =Z7-AZ7 -> 1150000000
A8: =CONCATENATE(B8,C8,D8,E8,F8,G8,H8,I8,J8,K8,L8,M8,N8) -> СКБСЖРозницаWMЛайфНовыйНСЖ_КБНСЖ с КэшбекомРегулярнаяНовый | B8: СКБСЖ | C8: =IFERROR(VLOOKUP(D8,Каналы!$B:$C,2,0),"") -> Розница | D8: WM | H8: Лайф | I8: Новый | K8: НСЖ_КБ | L8: НСЖ с Кэшбеком | M8: Регулярная | N8: Новый | O8: -14180000 | P8: 5800000 | Q8: 8900000 | R8: -2130000 | S8: 3880000 | T8: 9560000 | U8: 12680000 | V8: -3880000 | W8: -2150000 | X8: 5500000 | Y8: 5500000 | Z8: 5500000 | AA8: =SUM(O8:Z8) -> 34980000 | AB8: 2000000 | AC8: 2500000 | AD8: 2500000 | AE8: 2500000 | AF8: 2500000 | AG8: 4000000 | AH8: 4000000 | AI8: 4000000 | AJ8: 5000000 | AK8: 5000000 | AL8: 5000000 | AM8: 5000000 | AN8: =SUM(AB8:AM8) -> 44000000 | AW8: ок | AX8: 5500000 | AY8: 5500000 | AZ8: 5500000 | BA8: =X8-AX8 -> 0 | BB8: =Y8-AY8 -> 0 | BC8: =Z8-AZ8 -> 0
A9: =CONCATENATE(B9,C9,D9,E9,F9,G9,H9,I9,J9,K9,L9,M9,N9) -> СКБСЖРозницаБанкострахованиеЛайфСКБЖИндив.пенсияИндив ПенсияРегулярнаяНовый | B9: СКБСЖ | C9: =IFERROR(VLOOKUP(D9,Каналы!$B:$C,2,0),"") -> Розница | D9: Банкострахование | H9: Лайф | I9: СКБЖ | K9: Индив.пенсия | L9: Индив Пенсия | M9: Регулярная | N9: Новый | V9: -0.01 | AA9: =SUM(O9:Z9) -> -0.01 | AN9: =SUM(AB9:AM9) -> 0 | AW9: 0 | BA9: =X9-AX9 -> 0 | BB9: =Y9-AY9 -> 0 | BC9: =Z9-AZ9 -> 0
A10: =CONCATENATE(B10,C10,D10,E10,F10,G10,H10,I10,J10,K10,L10,M10,N10) -> СКБСЖРозницаБанкострахованиеЛайфСКБЖИндив.пенсияИндив ПенсияРегулярнаяПролонгация | B10: СКБСЖ | C10: =IFERROR(VLOOKUP(D10,Каналы!$B:$C,2,0),"") -> Розница | D10: Банкострахование | H10: Лайф | I10: СКБЖ | K10: Индив.пенсия | L10: Индив Пенсия | M10: Регулярная | N10: Пролонгация | U10: 373954.08 | AA10: =SUM(O10:Z10) -> 373954.08 | AN10: =SUM(AB10:AM10) -> 0 | AW10: 0 | BA10: =X10-AX10 -> 0 | BB10: =Y10-AY10 -> 0 | BC10: =Z10-AZ10 -> 0
A11: =CONCATENATE(B11,C11,D11,E11,F11,G11,H11,I11,J11,K11,L11,M11,N11) -> СКБСЖРозницаБанкострахованиеЛайфСКБЖНСЖДело жизниЕдиновременнаяНовый | B11: СКБСЖ | C11: =IFERROR(VLOOKUP(D11,Каналы!$B:$C,2,0),"") -> Розница | D11: Банкострахование | H11: Лайф | I11: СКБЖ | K11: НСЖ | L11: Дело жизни | M11: Единовременная | N11: Новый | O11: 298190000 | P11: 304060000 | Q11: 400000000 | R11: 442256762 | S11: 344820997 | T11: 226560433 | U11: 205585836 | V11: 345433682 | W11: 322057921 | X11: 320000000 | Y11: 320000000 | Z11: 320000000 | AA11: =SUM(O11:Z11) -> 3848965631 | AB11: 200000000 | AC11: 250000000 | AD11: 250000000 | AE11: 300000000 | AF11: 200000000 | AG11: 300000000 | AH11: 300000000 | AI11: 300000000 | AJ11: 350000000 | AK11: 350000000 | AL11: 350000000 | AM11: 350000000 | AN11: =SUM(AB11:AM11) -> 3500000000 | AW11: подняли до уровня 3 кв | AX11: 167000000 | AY11: 167000000 | AZ11: 167000000 | BA11: =X11-AX11 -> 153000000 | BB11: =Y11-AY11 -> 153000000 | BC11: =Z11-AZ11 -> 153000000
A12: =CONCATENATE(B12,C12,D12,E12,F12,G12,H12,I12,J12,K12,L12,M12,N12) -> СКБСЖРозницаБанкострахованиеЛайфСКБЖНСЖДело жизниРегулярнаяПролонгация | B12: СКБСЖ | C12: =IFERROR(VLOOKUP(D12,Каналы!$B:$C,2,0),"") -> Розница | D12: Банкострахование | H12: Лайф | I12: СКБЖ | K12: НСЖ | L12: Дело жизни | M12: Регулярная | N12: Пролонгация | P12: 30000 | T12: 50000 | AA12: =SUM(O12:Z12) -> 80000 | AN12: =SUM(AB12:AM12) -> 0 | AW12: 0 | BA12: =X12-AX12 -> 0 | BB12: =Y12-AY12 -> 0 | BC12: =Z12-AZ12 -> 0
A13: =CONCATENATE(B13,C13,D13,E13,F13,G13,H13,I13,J13,K13,L13,M13,N13) -> СКБСЖРозницаБанкострахованиеЛайфСКБЖНСЖДетский капиталЕдиновременнаяНовый | B13: СКБСЖ | C13: =IFERROR(VLOOKUP(D13,Каналы!$B:$C,2,0),"") -> Розница | D13: Банкострахование | H13: Лайф | I13: СКБЖ | K13: НСЖ | L13: Детский капитал | M13: Единовременная | N13: Новый | R13: 19800000 | S13: 16540000 | T13: 9280000 | U13: 10340000 | V13: 11910000 | W13: 7279079 | X13: 10000000 | Y13: 10000000 | Z13: 10000000 | AA13: =SUM(O13:Z13) -> 105149079 | AB13: 10000000 | AC13: 10000000 | AD13: 10000000 | AE13: 10000000 | AF13: 10000000 | AG13: 10000000 | AH13: 12000000 | AI13: 12000000 | AJ13: 12000000 | AK13: 15000000 | AL13: 15000000 | AM13: 15000000 | AN13: =SUM(AB13:AM13) -> 141000000 | AW13: добавлено по факту 3 кв | BA13: =X13-AX13 -> 10000000 | BB13: =Y13-AY13 -> 10000000 | BC13: =Z13-AZ13 -> 10000000
A14: =CONCATENATE(B14,C14,D14,E14,F14,G14,H14,I14,J14,K14,L14,M14,N14) -> СКБСЖРозницаБанкострахованиеЛайфСКБЖНСЖМаксимальная выгодаРегулярнаяПролонгация | B14: СКБСЖ | C14: =IFERROR(VLOOKUP(D14,Каналы!$B:$C,2,0),"") -> Розница | D14: Банкострахование | H14: Лайф | I14: СКБЖ | K14: НСЖ | L14: Максимальная выгода | M14: Регулярная | N14: Пролонгация | O14: 19330000 | P14: 17660000 | Q14: 11250000 | R14: 5810000 | S14: 9710000 | T14: 23660000 | U14: 18560000 | V14: 12300000 | W14: 21420000 | X14: 17500000 | Y14: 17500000 | Z14: 18000000 | AA14: =SUM(O14:Z14) -> 192700000 | AN14: =SUM(AB14:AM14) -> 0 | AW14: подняли до уровня 3 кв | AX14: 3250000 | AY14: 3250000 | AZ14: 3250000 | BA14: =X14-AX14 -> 14250000 | BB14: =Y14-AY14 -> 14250000 | BC14: =Z14-AZ14 -> 14750000
A15: =CONCATENATE(B15,C15,D15,E15,F15,G15,H15,I15,J15,K15,L15,M15,N15) -> СКБСЖРозницаБанкострахованиеЛайфСКБЖНСЖПрочее (СКБЖ)ЕдиновременнаяНовый | B15: СКБСЖ | C15: =IFERROR(VLOOKUP(D15,Каналы!$B:$C,2,0),"") -> Розница | D15: Банкострахование | H15: Лайф | I15: СКБЖ | K15: НСЖ | L15: Прочее (СКБЖ) | M15: Единовременная | N15: Новый | O15: 9181746 | P15: 12461991 | Q15: 13482629 | R15: 2856378 | AA15: =SUM(O15:Z15) -> 37982744 | AN15: =SUM(AB15:AM15) -> 0 | AW15: 0 | BA15: =X15-AX15 -> 0 | BB15: =Y15-AY15 -> 0 | BC15: =Z15-AZ15 -> 0
A16: =CONCATENATE(B16,C16,D16,E16,F16,G16,H16,I16,J16,K16,L16,M16,N16) -> СКБСЖРозницаБанкострахованиеЛайфСКБЖНСЖПрочее (СКБЖ)РегулярнаяНовый | B16: СКБСЖ | C16: =IFERROR(VLOOKUP(D16,Каналы!$B:$C,2,0),"") -> Розница | D16: Банкострахование | H16: Лайф | I16: СКБЖ | K16: НСЖ | L16: Прочее (СКБЖ) | M16: Регулярная | N16: Новый | O16: 9126664.7 | P16: 5379997.2 | Q16: 6099997.8 | R16: 5220004.4 | S16: 4568462.5 | T16: 3797270 | U16: 3774374.8 | V16: 2502657.2 | W16: 1696500.9 | X16: 3800000 | Y16: 2500000 | Z16: 1700000 | AA16: =SUM(O16:Z16) -> 50165929 | AN16: =SUM(AB16:AM16) -> 0 | AW16: подняли до уровня 3 кв | BA16: =X16-AX16 -> 3800000 | BB16: =Y16-AY16 -> 2500000 | BC16: =Z16-AZ16 -> 1700000
A17: =CONCATENATE(B17,C17,D17,E17,F17,G17,H17,I17,J17,K17,L17,M17,N17) -> СКБСЖРозницаБанкострахованиеЛайфСКБЖНСЖПрочее (СКБЖ)РегулярнаяПролонгация | B17: СКБСЖ | C17: =IFERROR(VLOOKUP(D17,Каналы!$B:$C,2,0),"") -> Розница | D17: Банкострахование | H17: Лайф | I17: СКБЖ | K17: НСЖ | L17: Прочее (СКБЖ) | M17: Регулярная | N17: Пролонгация | O17: 4385385.4 | P17: 1848439.5 | Q17: 7086679.5 | R17: 2877013.2 | S17: 6254546.3 | T17: 5401937.5 | U17: 4377641.4 | V17: 4775136.2 | W17: 4447599 | X17: 4400000 | Y17: 4800000 | Z17: 4500000 | AA17: =SUM(O17:Z17) -> 55154378 | AN17: =SUM(AB17:AM17) -> 0 | AW17: подняли до уровня 3 кв | BA17: =X17-AX17 -> 4400000 | BB17: =Y17-AY17 -> 4800000 | BC17: =Z17-AZ17 -> 4500000
A18: =CONCATENATE(B18,C18,D18,E18,F18,G18,H18,I18,J18,K18,L18,M18,N18) -> СКБСЖРозницаБанкострахованиеНон-лайфСКБЖНСДело жизниЕдиновременнаяНовый | B18: СКБСЖ | C18: =IFERROR(VLOOKUP(D18,Каналы!$B:$C,2,0),"") -> Розница | D18: Банкострахование | H18: Нон-лайф | I18: СКБЖ | K18: НС | L18: Дело жизни | M18: Единовременная | N18: Новый | R18: 1273238 | S18: 1089003 | T18: 699567 | U18: 674164 | V18: 1126318 | W18: 1072079 | X18: 1049354.8 | Y18: 1043389.2 | Z18: 1065228.5 | AA18: =SUM(O18:Z18) -> 9092341.5 | AN18: =SUM(AB18:AM18) -> 0 | AW18: расчет | BA18: =X18-AX18 -> 1049354.8 | BB18: =Y18-AY18 -> 1043389.2 | BC18: =Z18-AZ18 -> 1065228.5
A19: =CONCATENATE(B19,C19,D19,E19,F19,G19,H19,I19,J19,K19,L19,M19,N19) -> СКБСЖРозницаБанкострахованиеНон-лайфСКБЖНСНСЕдиновременнаяНовый | B19: СКБСЖ | C19: =IFERROR(VLOOKUP(D19,Каналы!$B:$C,2,0),"") -> Розница | D19: Банкострахование | H19: Нон-лайф | I19: СКБЖ | K19: НС | L19: НС | M19: Единовременная | N19: Новый | O19: 48254 | P19: 58009 | Q19: 67371 | R19: 13622 | AA19: =SUM(O19:Z19) -> 187256 | AN19: =SUM(AB19:AM19) -> 0 | AW19: 0 | BA19: =X19-AX19 -> 0 | BB19: =Y19-AY19 -> 0 | BC19: =Z19-AZ19 -> 0
A20: =CONCATENATE(B20,C20,D20,E20,F20,G20,H20,I20,J20,K20,L20,M20,N20) -> СКБСЖРозницаБанкострахованиеНон-лайфСКБЖНСНСРегулярнаяНовый | B20: СКБСЖ | C20: =IFERROR(VLOOKUP(D20,Каналы!$B:$C,2,0),"") -> Розница | D20: Банкострахование | H20: Нон-лайф | I20: СКБЖ | K20: НС | L20: НС | M20: Регулярная | N20: Новый | O20: 2252.64 | P20: 1484.52 | Q20: 551.03 | R20: 384.46 | S20: 374.29 | T20: 396.04 | U20: 290.54 | V20: 281.8 | W20: 283.62 | X20: 300 | Y20: 300 | Z20: 300 | AA20: =SUM(O20:Z20) -> 7198.94 | AN20: =SUM(AB20:AM20) -> 0 | AW20: подняли до уровня 3 кв | BA20: =X20-AX20 -> 300 | BB20: =Y20-AY20 -> 300 | BC20: =Z20-AZ20 -> 300
A21: =CONCATENATE(B21,C21,D21,E21,F21,G21,H21,I21,J21,K21,L21,M21,N21) -> СКБСЖРозницаБанкострахованиеНон-лайфСКБЖНСНСРегулярнаяПролонгация | B21: СКБСЖ | C21: =IFERROR(VLOOKUP(D21,Каналы!$B:$C,2,0),"") -> Розница | D21: Банкострахование | H21: Нон-лайф | I21: СКБЖ | K21: НС | L21: НС | M21: Регулярная | N21: Пролонгация | O21: 4428540 | P21: 4067644.8 | Q21: 4066931.9 | R21: 4266778.6 | S21: 4555055.6 | T21: 3888445.4 | U21: 3958772.4 | V21: 3474961.9 | W21: 3155161.1 | X21: 3000000 | Y21: 3000000 | Z21: 3000000 | AA21: =SUM(O21:Z21) -> 44862292 | AN21: =SUM(AB21:AM21) -> 0 | AW21: ок | AX21: 3000000 | AY21: 3000000 | AZ21: 3000000 | BA21: =X21-AX21 -> 0 | BB21: =Y21-AY21 -> 0 | BC21: =Z21-AZ21 -> 0
A22: =CONCATENATE(B22,C22,D22,E22,F22,G22,H22,I22,J22,K22,L22,M22,N22) -> СКБСЖРозницаWMЛайфНовыйОтдел заботыГКГибкий курсЕдиновременнаяНовый | B22: СКБСЖ | C22: =IFERROR(VLOOKUP(D22,Каналы!$B:$C,2,0),"") -> Розница | D22: WM | H22: Лайф | I22: Новый | J22: Отдел заботы | K22: ГК | L22: Гибкий курс | M22: Единовременная | N22: Новый | P22: 170000 | Q22: 13210990 | R22: 2860000 | S22: 66890000 | T22: 6982000 | U22: 7119907 | V22: 9240000 | W22: 10773123 | X22: 7150000 | Y22: 9250000 | Z22: 10800000 | AA22: =SUM(O22:Z22) -> 1.4444602e+08 | AN22: =SUM(AB22:AM22) -> 0 | AW22: добавлено по факту 3 кв | BA22: =X22-AX22 -> 7150000 | BB22: =Y22-AY22 -> 9250000 | BC22: =Z22-AZ22 -> 10800000
A23: =CONCATENATE(B23,C23,D23,E23,F23,G23,H23,I23,J23,K23,L23,M23,N23) -> СКБСЖРозницаWMЛайфНовыйНСЖ_КБНСЖ с КэшбекомРегулярнаяНовый | B23: СКБСЖ | C23: =IFERROR(VLOOKUP(D23,Каналы!$B:$C,2,0),"") -> Розница | D23: WM | H23: Лайф | I23: Новый | K23: НСЖ_КБ | L23: НСЖ с Кэшбеком | M23: Регулярная | N23: Новый | O23: 3020000 | P23: 6540000 | Q23: 4950000 | R23: 3800000 | S23: 1970000 | T23: 1420000 | U23: 8950000 | V23: 12330000 | W23: 11710000 | X23: 3500000 | Y23: 3500000 | Z23: 3500000 | AA23: =SUM(O23:Z23) -> 65190000 | AN23: =SUM(AB23:AM23) -> 0 | AW23: почему было обнулено окт + нояб? Вернули | AZ23: 3500000 | BA23: =X23-AX23 -> 3500000 | BB23: =Y23-AY23 -> 3500000 | BC23: =Z23-AZ23 -> 0
A24: =CONCATENATE(B24,C24,D24,E24,F24,G24,H24,I24,J24,K24,L24,M24,N24) -> СКБСЖРозницаWMЛайфНовыйНСЖ_КБНСЖ с КэшбекомРегулярнаяПролонгация | B24: СКБСЖ | C24: =IFERROR(VLOOKUP(D24,Каналы!$B:$C,2,0),"") -> Розница | D24: WM | H24: Лайф | I24: Новый | K24: НСЖ_КБ | L24: НСЖ с Кэшбеком | M24: Регулярная | N24: Пролонгация | O24: 1120000 | AA24: =SUM(O24:Z24) -> 1120000 | AN24: =SUM(AB24:AM24) -> 0 | AW24: 0 | BA24: =X24-AX24 -> 0 | BB24: =Y24-AY24 -> 0 | BC24: =Z24-AZ24 -> 0
A25: =CONCATENATE(B25,C25,D25,E25,F25,G25,H25,I25,J25,K25,L25,M25,N25) -> СКБСЖРозницаWMЛайфСКБЖИСЖ_СИВПрочее (СИВ)ЕдиновременнаяНовый | B25: СКБСЖ | C25: =IFERROR(VLOOKUP(D25,Каналы!$B:$C,2,0),"") -> Розница | D25: WM | H25: Лайф | I25: СКБЖ | K25: ИСЖ_СИВ | L25: Прочее (СИВ) | M25: Единовременная | N25: Новый | O25: 0 | P25: 85000000 | Q25: 60000000 | R25: 80000000 | S25: 0 | T25: 0 | U25: 0 | V25: 30000000 | W25: 0 | AA25: =SUM(O25:Z25) -> 255000000 | AN25: =SUM(AB25:AM25) -> 0 | AW25: не ставим прогноз | BA25: =X25-AX25 -> 0 | BB25: =Y25-AY25 -> 0 | BC25: =Z25-AZ25 -> 0
A26: =CONCATENATE(B26,C26,D26,E26,F26,G26,H26,I26,J26,K26,L26,M26,N26) -> СКБСЖРозницаРозница (прочее)ЛайфСКБЖНСЖДело жизниЕдиновременнаяНовый | B26: СКБСЖ | C26: =IFERROR(VLOOKUP(D26,Каналы!$B:$C,2,0),"") -> Розница | D26: Розница (прочее) | H26: Лайф | I26: СКБЖ | K26: НСЖ | L26: Дело жизни | M26: Единовременная | N26: Новый | AA26: =SUM(O26:Z26) -> 0 | AN26: =SUM(AB26:AM26) -> 0 | AW26: обнулен прогноз на этой строке, т.к. заложен выше | BA26: =X26-AX26 -> 0 | BB26: =Y26-AY26 -> 0 | BC26: =Z26-AZ26 -> 0
A27: =CONCATENATE(B27,C27,D27,E27,F27,G27,H27,I27,J27,K27,L27,M27,N27) -> СКБСЖРозницаРозница (прочее)ЛайфСКБЖНСЖПрочее (СКБЖ)РегулярнаяНовый | B27: СКБСЖ | C27: =IFERROR(VLOOKUP(D27,Каналы!$B:$C,2,0),"") -> Розница | D27: Розница (прочее) | H27: Лайф | I27: СКБЖ | K27: НСЖ | L27: Прочее (СКБЖ) | M27: Регулярная | N27: Новый | AA27: =SUM(O27:Z27) -> 0 | AN27: =SUM(AB27:AM27) -> 0 | AW27: обнулено, нет факта | BA27: =X27-AX27 -> 0 | BB27: =Y27-AY27 -> 0 | BC27: =Z27-AZ27 -> 0
A28: =CONCATENATE(B28,C28,D28,E28,F28,G28,H28,I28,J28,K28,L28,M28,N28) -> СКБСЖРозницаРозница (прочее)ЛайфСКБЖНСЖПрочее (СКБЖ)РегулярнаяПролонгация | B28: СКБСЖ | C28: =IFERROR(VLOOKUP(D28,Каналы!$B:$C,2,0),"") -> Розница | D28: Розница (прочее) | H28: Лайф | I28: СКБЖ | K28: НСЖ | L28: Прочее (СКБЖ) | M28: Регулярная | N28: Пролонгация | AA28: =SUM(O28:Z28) -> 0 | AN28: =SUM(AB28:AM28) -> 0 | AW28: обнулено, нет факта | BA28: =X28-AX28 -> 0 | BB28: =Y28-AY28 -> 0 | BC28: =Z28-AZ28 -> 0
A29: =CONCATENATE(B29,C29,D29,E29,F29,G29,H29,I29,J29,K29,L29,M29,N29) -> СКБСЖРозницаWMЛайфСКБЖНСЖ_СИВCiti ComfortРегулярнаяПролонгация | B29: СКБСЖ | C29: =IFERROR(VLOOKUP(D29,Каналы!$B:$C,2,0),"") -> Розница | D29: WM | H29: Лайф | I29: СКБЖ | K29: НСЖ_СИВ | L29: Citi Comfort | M29: Регулярная | N29: Пролонгация | O29: 18410377 | P29: 21487153 | Q29: 47554502 | R29: 19857180 | S29: 38031110 | T29: 29276082 | U29: 36137478 | V29: 28538487 | W29: 18640075 | X29: 36500000 | Y29: 29000000 | Z29: 19000000 | AA29: =SUM(O29:Z29) -> 3.4243244e+08 | AB29: =O29*0.5 -> 9205188.3 | AC29: =P29*0.5 -> 10743576 | AD29: =Q29*0.5 -> 23777251 | AE29: =R29*0.5 -> 9928590.2 | AF29: =S29*0.5 -> 19015555 | AG29: =T29*0.5 -> 14638041 | AH29: =U29*0.5 -> 18068739 | AI29: =V29*0.5 -> 14269244 | ... AM29: =Z29*0.5 -> 9500000 | AN29: =SUM(AB29:AM29) -> 1.7121622e+08 | AW29: подняли до уровня 3 кв | BA29: =X29-AX29 -> 36500000 | BB29: =Y29-AY29 -> 29000000 | BC29: =Z29-AZ29 -> 19000000
A30: =CONCATENATE(B30,C30,D30,E30,F30,G30,H30,I30,J30,K30,L30,M30,N30) -> СКБСЖРозницаWMЛайфСКБЖНСЖ_СИВCiti HealthЕдиновременнаяНовый | B30: СКБСЖ | C30: =IFERROR(VLOOKUP(D30,Каналы!$B:$C,2,0),"") -> Розница | D30: WM | H30: Лайф | I30: СКБЖ | K30: НСЖ_СИВ | L30: Citi Health | M30: Единовременная | N30: Новый | O30: 0 | W30: 0 | AA30: =SUM(O30:Z30) -> 0 | AN30: =SUM(AB30:AM30) -> 0 | AW30: 0 | BA30: =X30-AX30 -> 0 | BB30: =Y30-AY30 -> 0 | BC30: =Z30-AZ30 -> 0
A31: =CONCATENATE(B31,C31,D31,E31,F31,G31,H31,I31,J31,K31,L31,M31,N31) -> СКБСЖРозницаWMЛайфСКБЖНСЖ_СИВCiti HealthРегулярнаяПролонгация | B31: СКБСЖ | C31: =IFERROR(VLOOKUP(D31,Каналы!$B:$C,2,0),"") -> Розница | D31: WM | H31: Лайф | I31: СКБЖ | K31: НСЖ_СИВ | L31: Citi Health | M31: Регулярная | N31: Пролонгация | O31: 20658385 | P31: 30591993 | Q31: 23807663 | R31: 57329914 | S31: 32240018 | T31: 43752002 | U31: 30135269 | V31: 18398511 | W31: 18218176 | X31: 31200000 | Y31: 18500000 | Z31: 18500000 | AA31: =SUM(O31:Z31) -> 3.4333193e+08 | AB31: =O31*0.5 -> 10329193 | AC31: =P31*0.5 -> 15295996 | AD31: =Q31*0.5 -> 11903832 | AE31: =R31*0.5 -> 28664957 | AF31: =S31*0.5 -> 16120009 | AG31: =T31*0.5 -> 21876001 | AH31: =U31*0.5 -> 15067634 | AI31: =V31*0.5 -> 9199255.3 | ... AM31: =Z31*0.5 -> 9250000 | AN31: =SUM(AB31:AM31) -> 1.7166597e+08 | AW31: подняли до уровня 3 кв | BA31: =X31-AX31 -> 31200000 | BB31: =Y31-AY31 -> 18500000 | BC31: =Z31-AZ31 -> 18500000
A32: =CONCATENATE(B32,C32,D32,E32,F32,G32,H32,I32,J32,K32,L32,M32,N32) -> СКБСЖРозницаWMЛайфСКБЖНСЖ_СИВCiti KidsЕдиновременнаяНовый | B32: СКБСЖ | C32: =IFERROR(VLOOKUP(D32,Каналы!$B:$C,2,0),"") -> Розница | D32: WM | H32: Лайф | I32: СКБЖ | K32: НСЖ_СИВ | L32: Citi Kids | M32: Единовременная | N32: Новый | O32: 0 | P32: 0 | Q32: 0 | R32: 0 | S32: 0 | T32: 0 | U32: 0 | V32: 0 | W32: 0 | AA32: =SUM(O32:Z32) -> 0 | AN32: =SUM(AB32:AM32) -> 0 | AW32: 0 | BA32: =X32-AX32 -> 0 | BB32: =Y32-AY32 -> 0 | BC32: =Z32-AZ32 -> 0
A33: =CONCATENATE(B33,C33,D33,E33,F33,G33,H33,I33,J33,K33,L33,M33,N33) -> СКБСЖРозницаWMЛайфСКБЖНСЖ_СИВCiti KidsРегулярнаяПролонгация | B33: СКБСЖ | C33: =IFERROR(VLOOKUP(D33,Каналы!$B:$C,2,0),"") -> Розница | D33: WM | H33: Лайф | I33: СКБЖ | K33: НСЖ_СИВ | L33: Citi Kids | M33: Регулярная | N33: Пролонгация | O33: 5831098 | P33: 6117249.5 | Q33: 7756441.3 | R33: 4418466.3 | S33: 5748158.3 | T33: 9817342.2 | U33: 3900115.4 | V33: 6670744.4 | W33: 10019313 | X33: 400000 | Y33: 6700000 | Z33: 10000000 | AA33: =SUM(O33:Z33) -> 77378929 | AB33: =O33*0.5 -> 2915549 | AC33: =P33*0.5 -> 3058624.7 | AD33: =Q33*0.5 -> 3878220.6 | AE33: =R33*0.5 -> 2209233.1 | AF33: =S33*0.5 -> 2874079.2 | AG33: =T33*0.5 -> 4908671.1 | AH33: =U33*0.5 -> 1950057.7 | AI33: =V33*0.5 -> 3335372.2 | ... AM33: =Z33*0.5 -> 5000000 | AN33: =SUM(AB33:AM33) -> 38689464 | AW33: подняли до уровня 3 кв | BA33: =X33-AX33 -> 400000 | BB33: =Y33-AY33 -> 6700000 | BC33: =Z33-AZ33 -> 10000000
A34: =CONCATENATE(B34,C34,D34,E34,F34,G34,H34,I34,J34,K34,L34,M34,N34) -> СКБСЖРозницаWMЛайфСКБЖНСЖ_СИВCiti PremiumЕдиновременнаяНовый | B34: СКБСЖ | C34: =IFERROR(VLOOKUP(D34,Каналы!$B:$C,2,0),"") -> Розница | D34: WM | H34: Лайф | I34: СКБЖ | K34: НСЖ_СИВ | L34: Citi Premium | M34: Единовременная | N34: Новый | P34: 0 | V34: 0 | AA34: =SUM(O34:Z34) -> 0 | AN34: =SUM(AB34:AM34) -> 0 | AW34: 0 | BA34: =X34-AX34 -> 0 | BB34: =Y34-AY34 -> 0 | BC34: =Z34-AZ34 -> 0
A35: =CONCATENATE(B35,C35,D35,E35,F35,G35,H35,I35,J35,K35,L35,M35,N35) -> СКБСЖРозницаWMЛайфСКБЖНСЖ_СИВCiti PremiumРегулярнаяПролонгация | B35: СКБСЖ | C35: =IFERROR(VLOOKUP(D35,Каналы!$B:$C,2,0),"") -> Розница | D35: WM | H35: Лайф | I35: СКБЖ | K35: НСЖ_СИВ | L35: Citi Premium | M35: Регулярная | N35: Пролонгация | O35: 13187633 | P35: 12480846 | Q35: 7726525.5 | R35: 19139304 | S35: 15472515 | T35: 18532815 | U35: 14041567 | V35: 11396480 | W35: 15022084 | X35: 14000000 | Y35: 11400000 | Z35: 15000000 | AA35: =SUM(O35:Z35) -> 1.6739977e+08 | AB35: =O35*0.5 -> 6593816.4 | AC35: =P35*0.5 -> 6240423.2 | AD35: =Q35*0.5 -> 3863262.8 | AE35: =R35*0.5 -> 9569651.9 | AF35: =S35*0.5 -> 7736257.5 | AG35: =T35*0.5 -> 9266407.7 | AH35: =U35*0.5 -> 7020783.3 | AI35: =V35*0.5 -> 5698239.9 | ... AM35: =Z35*0.5 -> 7500000 | AN35: =SUM(AB35:AM35) -> 83699885 | AW35: подняли до уровня 3 кв | BA35: =X35-AX35 -> 14000000 | BB35: =Y35-AY35 -> 11400000 | BC35: =Z35-AZ35 -> 15000000
A36: =CONCATENATE(B36,C36,D36,E36,F36,G36,H36,I36,J36,K36,L36,M36,N36) -> СКБСЖРозницаWMЛайфСКБЖНСЖ_СИВПрочее (СИВ)ЕдиновременнаяНовый | B36: СКБСЖ | C36: =IFERROR(VLOOKUP(D36,Каналы!$B:$C,2,0),"") -> Розница | D36: WM | H36: Лайф | I36: СКБЖ | K36: НСЖ_СИВ | L36: Прочее (СИВ) | M36: Единовременная | N36: Новый | P36: 0 | AA36: =SUM(O36:Z36) -> 0 | AN36: =SUM(AB36:AM36) -> 0 | AW36: 0 | BA36: =X36-AX36 -> 0 | BB36: =Y36-AY36 -> 0 | BC36: =Z36-AZ36 -> 0
A37: =CONCATENATE(B37,C37,D37,E37,F37,G37,H37,I37,J37,K37,L37,M37,N37) -> СКБСЖРозницаWMЛайфСКБЖНСЖ_СИВПрочее (СИВ)РегулярнаяПролонгация | B37: СКБСЖ | C37: =IFERROR(VLOOKUP(D37,Каналы!$B:$C,2,0),"") -> Розница | D37: WM | H37: Лайф | I37: СКБЖ | K37: НСЖ_СИВ | L37: Прочее (СИВ) | M37: Регулярная | N37: Пролонгация | O37: 503886.87 | P37: 5027505.5 | Q37: 1765599.7 | R37: 4102683.1 | S37: 1189403.2 | T37: 1983821.4 | U37: 1014276.9 | V37: 1549964.6 | W37: 2316840.2 | X37: 1000000 | Y37: 1500000 | Z37: 2350000 | AA37: =SUM(O37:Z37) -> 24303982 | AB37: =O37*0.5 -> 251943.44 | AC37: =P37*0.5 -> 2513752.8 | AD37: =Q37*0.5 -> 882799.84 | AE37: =R37*0.5 -> 2051341.6 | AF37: =S37*0.5 -> 594701.6 | AG37: =T37*0.5 -> 991910.69 | AH37: =U37*0.5 -> 507138.43 | AI37: =V37*0.5 -> 774982.32 | ... AM37: =Z37*0.5 -> 1175000 | AN37: =SUM(AB37:AM37) -> 12151991 | AW37: подняли до уровня 3 кв | BA37: =X37-AX37 -> 1000000 | BB37: =Y37-AY37 -> 1500000 | BC37: =Z37-AZ37 -> 2350000
A38: =CONCATENATE(B38,C38,D38,E38,F38,G38,H38,I38,J38,K38,L38,M38,N38) -> СКБСЖРозницаWMЛайфСКБЖНСЖ_СИВСтабильный курсЕдиновременнаяНовый | B38: СКБСЖ | C38: =IFERROR(VLOOKUP(D38,Каналы!$B:$C,2,0),"") -> Розница | D38: WM | H38: Лайф | I38: СКБЖ | K38: НСЖ_СИВ | L38: Стабильный курс | M38: Единовременная | N38: Новый | O38: 26751017 | P38: 54354258 | Q38: 94008406 | R38: 1.0344756e+08 | S38: 74110009 | T38: 1.3434973e+08 | U38: 65855565 | V38: 1.1670813e+08 | W38: 19812750 | X38: 67000000 | Y38: 67000000 | Z38: 67000000 | AA38: =SUM(O38:Z38) -> 8.9039742e+08 | AB38: 20000000 | AC38: 25000000 | AD38: 40000000 | AE38: 50000000 | AF38: 30000000 | AG38: 50000000 | AH38: 50000000 | AI38: 50000000 | AJ38: 70000000 | AK38: 70000000 | AL38: 70000000 | AM38: 70000000 | AN38: =SUM(AB38:AM38) -> 595000000 | AW38: подняли до уровня 3 кв | AX38: 56000000 | AY38: 25000000 | AZ38: 25000000 | BA38: =X38-AX38 -> 11000000 | BB38: =Y38-AY38 -> 42000000 | BC38: =Z38-AZ38 -> 42000000
A39: =CONCATENATE(B39,C39,D39,E39,F39,G39,H39,I39,J39,K39,L39,M39,N39) -> СКБСЖРозницаWMЛайфСКБЖНСЖ_СИВСтабильный курсРегулярнаяНовый | B39: СКБСЖ | C39: =IFERROR(VLOOKUP(D39,Каналы!$B:$C,2,0),"") -> Розница | D39: WM | H39: Лайф | I39: СКБЖ | K39: НСЖ_СИВ | L39: Стабильный курс | M39: Регулярная | N39: Новый | O39: 431915.26 | P39: 1969383.9 | R39: 665749.29 | S39: 486687.65 | T39: 175422.25 | U39: 407935.73 | V39: 49748.26 | AA39: =SUM(O39:Z39) -> 4186842.4 | AN39: =SUM(AB39:AM39) -> 0 | AW39: 0 | BA39: =X39-AX39 -> 0 | BB39: =Y39-AY39 -> 0 | BC39: =Z39-AZ39 -> 0
A40: =CONCATENATE(B40,C40,D40,E40,F40,G40,H40,I40,J40,K40,L40,M40,N40) -> СКБСЖРозницаWMЛайфСКБЖНСЖ_СИВСтабильный курсРегулярнаяПролонгация | B40: СКБСЖ | C40: =IFERROR(VLOOKUP(D40,Каналы!$B:$C,2,0),"") -> Розница | D40: WM | H40: Лайф | I40: СКБЖ | K40: НСЖ_СИВ | L40: Стабильный курс | M40: Регулярная | N40: Пролонгация | P40: 1636296.9 | Q40: 1276658.3 | R40: 710630.34 | S40: 1989930.2 | T40: 1801710.7 | U40: 2818490 | V40: 3919556.7 | W40: 3441442.8 | X40: 79714940 | Y40: 73347001 | Z40: 1.6705824e+08 | AA40: =SUM(O40:Z40) -> 3.377149e+08 | AB40: =O40*0.5 -> 0 | AC40: =P40*0.5 -> 818148.47 | AD40: =Q40*0.5 -> 638329.17 | AE40: =R40*0.5 -> 355315.17 | AF40: =S40*0.5 -> 994965.12 | AG40: =T40*0.5 -> 900855.35 | AH40: =U40*0.5 -> 1409245 | AI40: =V40*0.5 -> 1959778.4 | ... AM40: =Z40*0.5 -> 83529119 | AN40: =SUM(AB40:AM40) -> 1.6885745e+08 | AW40: ок | AX40: 79714940 | AY40: 73347001 | AZ40: 1.6705824e+08 | BA40: =X40-AX40 -> 0 | BB40: =Y40-AY40 -> 0 | BC40: =Z40-AZ40 -> 0
A41: =CONCATENATE(B41,C41,D41,E41,F41,G41,H41,I41,J41,K41,L41,M41,N41) -> СКБСЖРозницаWMЛайфСКБЖНСЖ_СИВСила процентаЕдиновременнаяНовый | B41: СКБСЖ | C41: =IFERROR(VLOOKUP(D41,Каналы!$B:$C,2,0),"") -> Розница | D41: WM | H41: Лайф | I41: СКБЖ | K41: НСЖ_СИВ | L41: Сила процента | M41: Единовременная | N41: Новый | V41: 36750208 | W41: 63622878 | X41: 629000000 | Y41: 350000000 | Z41: 350000000 | AA41: =SUM(O41:Z41) -> 1.4293731e+09 | AB41: 50000000 | AC41: 50000000 | AD41: 150000000 | AE41: 150000000 | AF41: 100000000 | AG41: 250000000 | AH41: 250000000 | AI41: 250000000 | AJ41: 200000000 | AK41: 350000000 | AL41: 350000000 | AM41: 350000000 | AN41: =SUM(AB41:AM41) -> 2500000000 | AW41: ок | AX41: 629000000 | AY41: 350000000 | AZ41: 350000000 | BA41: =X41-AX41 -> 0 | BB41: =Y41-AY41 -> 0 | BC41: =Z41-AZ41 -> 0
A42: =CONCATENATE(B42,C42,D42,E42,F42,G42,H42,I42,J42,K42,L42,M42,N42) -> СКБСЖРозницаРозница (прочее)Нон-лайфСКБЖДМСДМСРегулярнаяНовый | B42: СКБСЖ | C42: =IFERROR(VLOOKUP(D42,Каналы!$B:$C,2,0),"") -> Розница | D42: Розница (прочее) | H42: Нон-лайф | I42: СКБЖ | K42: ДМС | L42: ДМС | M42: Регулярная | N42: Новый | Y42: 24112000 | AA42: =SUM(O42:Z42) -> 24112000 | AN42: =SUM(AB42:AM42) -> 0 | AW42: ок | AY42: 24112000 | BA42: =X42-AX42 -> 0 | BB42: =Y42-AY42 -> 0 | BC42: =Z42-AZ42 -> 0
A43: =CONCATENATE(B43,C43,D43,E43,F43,G43,H43,I43,J43,K43,L43,M43,N43) -> СКБСЖРозницаWMНон-лайфСКБЖДМС_СИВПрочее (СИВ)РегулярнаяПролонгация | B43: СКБСЖ | C43: =IFERROR(VLOOKUP(D43,Каналы!$B:$C,2,0),"") -> Розница | D43: WM | H43: Нон-лайф | I43: СКБЖ | K43: ДМС_СИВ | L43: Прочее (СИВ) | M43: Регулярная | N43: Пролонгация | O43: 86937.21 | P43: 0 | Q43: 52231.56 | R43: 19451.63 | S43: 48014.15 | T43: 112944.58 | U43: 0 | V43: 38708.2 | W43: -2700.99 | AA43: =SUM(O43:Z43) -> 355586.34 | AB43: =O43*0.5 -> 43468.605 | AC43: =P43*0.5 -> 0 | AD43: =Q43*0.5 -> 26115.78 | AE43: =R43*0.5 -> 9725.815 | AF43: =S43*0.5 -> 24007.075 | AG43: =T43*0.5 -> 56472.29 | AH43: =U43*0.5 -> 0 | AI43: =V43*0.5 -> 19354.1 | ... AM43: =Z43*0.5 -> 0 | AN43: =SUM(AB43:AM43) -> 177793.17 | AW43: 0 | BA43: =X43-AX43 -> 0 | BB43: =Y43-AY43 -> 0 | BC43: =Z43-AZ43 -> 0
A44: =CONCATENATE(B44,C44,D44,E44,F44,G44,H44,I44,J44,K44,L44,M44,N44) -> СКБСЖРозницаРозница (прочее)Нон-лайфСКБЖКСЖКСЖЕдиновременнаяНовый | B44: СКБСЖ | C44: =IFERROR(VLOOKUP(D44,Каналы!$B:$C,2,0),"") -> Розница | D44: Розница (прочее) | H44: Нон-лайф | I44: СКБЖ | K44: КСЖ | L44: КСЖ | M44: Единовременная | N44: Новый | O44: 6994506.4 | P44: 6031821.9 | Q44: 7127830 | R44: 8688472.9 | S44: 9601411.8 | T44: 7724261.5 | U44: 5209832.8 | V44: 6790333.6 | W44: 5058978.2 | X44: 5300000 | Y44: 6800000 | Z44: 5100000 | AA44: =SUM(O44:Z44) -> 80427449 | AB44: 5000000 | AC44: 5000000 | AD44: 5000000 | AE44: 5000000 | AF44: 5000000 | AG44: 5000000 | AH44: 5000000 | AI44: 5000000 | AJ44: 5000000 | AK44: 5000000 | AL44: 5000000 | AM44: 5000000 | AN44: =SUM(AB44:AM44) -> 60000000 | AW44: подняли до уровня 3 кв | AX44: 2500000 | AY44: 2500000 | AZ44: 2500000 | BA44: =X44-AX44 -> 2800000 | BB44: =Y44-AY44 -> 4300000 | BC44: =Z44-AZ44 -> 2600000
A45: =CONCATENATE(B45,C45,D45,E45,F45,G45,H45,I45,J45,K45,L45,M45,N45) -> СКБСЖРозницаРозница (прочее)Нон-лайфСКБЖКСЖКСЖРегулярнаяНовый | B45: СКБСЖ | C45: =IFERROR(VLOOKUP(D45,Каналы!$B:$C,2,0),"") -> Розница | D45: Розница (прочее) | H45: Нон-лайф | I45: СКБЖ | K45: КСЖ | L45: КСЖ | M45: Регулярная | N45: Новый | O45: 68.53 | P45: 108.79 | Q45: 70 | R45: 91.18 | S45: 89.76 | T45: 37.36 | U45: 63.19 | V45: 21.41 | W45: 13.44 | AA45: =SUM(O45:Z45) -> 563.66 | AN45: =SUM(AB45:AM45) -> 0 | AW45: 0 | BA45: =X45-AX45 -> 0 | BB45: =Y45-AY45 -> 0 | BC45: =Z45-AZ45 -> 0
A46: =CONCATENATE(B46,C46,D46,E46,F46,G46,H46,I46,J46,K46,L46,M46,N46) -> СКБСЖРозницаРозница (прочее)Нон-лайфСКБЖКСЖКСЖРегулярнаяПролонгация | B46: СКБСЖ | C46: =IFERROR(VLOOKUP(D46,Каналы!$B:$C,2,0),"") -> Розница | D46: Розница (прочее) | H46: Нон-лайф | I46: СКБЖ | K46: КСЖ | L46: КСЖ | M46: Регулярная | N46: Пролонгация | O46: 28937.75 | P46: 25307.52 | Q46: 25190 | R46: 24821.58 | S46: 23877.66 | T46: 23271.49 | U46: 22613.64 | V46: 22774.85 | W46: 21838.7 | X46: 23000 | Y46: 23000 | Z46: 22000 | AA46: =SUM(O46:Z46) -> 286633.19 | AN46: =SUM(AB46:AM46) -> 0 | AW46: подняли до уровня 3 кв | AX46: 9900 | AY46: 9900 | AZ46: 9900 | BA46: =X46-AX46 -> 13100 | BB46: =Y46-AY46 -> 13100 | BC46: =Z46-AZ46 -> 12100
A47: =CONCATENATE(B47,C47,D47,E47,F47,G47,H47,I47,J47,K47,L47,M47,N47) -> СКБСЖРозницаWMНон-лайфСКБЖКСЖ_СИВПрочее (СИВ)РегулярнаяНовый | B47: СКБСЖ | C47: =IFERROR(VLOOKUP(D47,Каналы!$B:$C,2,0),"") -> Розница | D47: WM | H47: Нон-лайф | I47: СКБЖ | K47: КСЖ_СИВ | L47: Прочее (СИВ) | M47: Регулярная | N47: Новый | R47: 0 | T47: 0 | AA47: =SUM(O47:Z47) -> 0 | AN47: =SUM(AB47:AM47) -> 0 | AW47: 0 | BA47: =X47-AX47 -> 0 | BB47: =Y47-AY47 -> 0 | BC47: =Z47-AZ47 -> 0
A48: =CONCATENATE(B48,C48,D48,E48,F48,G48,H48,I48,J48,K48,L48,M48,N48) -> СКБСЖРозницаWMНон-лайфСКБЖКСЖ_СИВПрочее (СИВ)РегулярнаяПролонгация | B48: СКБСЖ | C48: =IFERROR(VLOOKUP(D48,Каналы!$B:$C,2,0),"") -> Розница | D48: WM | H48: Нон-лайф | I48: СКБЖ | K48: КСЖ_СИВ | L48: Прочее (СИВ) | M48: Регулярная | N48: Пролонгация | O48: 462576.4 | P48: 413099.12 | Q48: 402065.43 | R48: -430844.41 | S48: -9312.31 | AA48: =SUM(O48:Z48) -> 837584.23 | AB48: =O48*0.5 -> 231288.2 | AC48: =P48*0.5 -> 206549.56 | AD48: =Q48*0.5 -> 201032.71 | AE48: =R48*0.5 -> -215422.21 | AF48: =S48*0.5 -> -4656.155 | AG48: =T48*0.5 -> 0 | AH48: =U48*0.5 -> 0 | AI48: =V48*0.5 -> 0 | ... AM48: =Z48*0.5 -> 0 | AN48: =SUM(AB48:AM48) -> 418792.11 | AW48: 0 | BA48: =X48-AX48 -> 0 | BB48: =Y48-AY48 -> 0 | BC48: =Z48-AZ48 -> 0
A49: =CONCATENATE(B49,C49,D49,E49,F49,G49,H49,I49,J49,K49,L49,M49,N49) -> СКБСЖРозницаРозница (прочее)Нон-лайфСКБЖНСНСРегулярнаяНовый | B49: СКБСЖ | C49: =IFERROR(VLOOKUP(D49,Каналы!$B:$C,2,0),"") -> Розница | D49: Розница (прочее) | H49: Нон-лайф | I49: СКБЖ | K49: НС | L49: НС | M49: Регулярная | N49: Новый | AA49: =SUM(O49:Z49) -> 0 | AN49: =SUM(AB49:AM49) -> 0 | AW49: 0 | BA49: =X49-AX49 -> 0 | BB49: =Y49-AY49 -> 0 | BC49: =Z49-AZ49 -> 0
A50: =CONCATENATE(B50,C50,D50,E50,F50,G50,H50,I50,J50,K50,L50,M50,N50) -> СКБСЖРозницаWMНон-лайфСКБЖНС_СИВПрочее (СИВ)РегулярнаяПролонгация | B50: СКБСЖ | C50: =IFERROR(VLOOKUP(D50,Каналы!$B:$C,2,0),"") -> Розница | D50: WM | H50: Нон-лайф | I50: СКБЖ | K50: НС_СИВ | L50: Прочее (СИВ) | M50: Регулярная | N50: Пролонгация | O50: 194550 | P50: 100440 | Q50: 153780 | R50: 98370 | S50: 129930 | T50: -28500 | U50: 337050 | V50: 146520 | W50: 117720 | X50: 340000 | Y50: 150000 | Z50: 120000 | AA50: =SUM(O50:Z50) -> 1859860 | AB50: =O50*0.5 -> 97275 | AC50: =P50*0.5 -> 50220 | AD50: =Q50*0.5 -> 76890 | AE50: =R50*0.5 -> 49185 | AF50: =S50*0.5 -> 64965 | AG50: =T50*0.5 -> -14250 | AH50: =U50*0.5 -> 168525 | AI50: =V50*0.5 -> 73260 | ... AM50: =Z50*0.5 -> 60000 | AN50: =SUM(AB50:AM50) -> 929930 | AW50: подняли до уровня 3 кв | BA50: =X50-AX50 -> 340000 | BB50: =Y50-AY50 -> 150000 | BC50: =Z50-AZ50 -> 120000
A51: =CONCATENATE(B51,C51,D51,E51,F51,G51,H51,I51,J51,K51,L51,M51,N51) -> СКБСЖРозницаWMНон-лайфСКБЖНСЖ_СИВ_ДМСCiti HealthЕдиновременнаяНовый | B51: СКБСЖ | C51: =IFERROR(VLOOKUP(D51,Каналы!$B:$C,2,0),"") -> Розница | D51: WM | H51: Нон-лайф | I51: СКБЖ | K51: НСЖ_СИВ_ДМС | L51: Citi Health | M51: Единовременная | N51: Новый | O51: 0 | W51: 0 | AA51: =SUM(O51:Z51) -> 0 | AN51: =SUM(AB51:AM51) -> 0 | AW51: 0 | BA51: =X51-AX51 -> 0 | BB51: =Y51-AY51 -> 0 | BC51: =Z51-AZ51 -> 0
A52: =CONCATENATE(B52,C52,D52,E52,F52,G52,H52,I52,J52,K52,L52,M52,N52) -> СКБСЖРозницаWMНон-лайфСКБЖНСЖ_СИВ_ДМСCiti HealthРегулярнаяПролонгация | B52: СКБСЖ | C52: =IFERROR(VLOOKUP(D52,Каналы!$B:$C,2,0),"") -> Розница | D52: WM | H52: Нон-лайф | I52: СКБЖ | K52: НСЖ_СИВ_ДМС | L52: Citi Health | M52: Регулярная | N52: Пролонгация | O52: 1719153.4 | P52: 2903457 | Q52: 3193643.3 | R52: 6788573.6 | S52: 3567001.3 | T52: 4466264.5 | U52: 3125808.8 | V52: 1918338.2 | W52: 1348743.4 | X52: 3236249.1 | Y52: 1928920.1 | Z52: 1369607.7 | AA52: =SUM(O52:Z52) -> 35565760 | AB52: =O52*0.5 -> 859576.72 | AC52: =P52*0.5 -> 1451728.5 | AD52: =Q52*0.5 -> 1596821.6 | AE52: =R52*0.5 -> 3394286.8 | AF52: =S52*0.5 -> 1783500.6 | AG52: =T52*0.5 -> 2233132.3 | AH52: =U52*0.5 -> 1562904.4 | AI52: =V52*0.5 -> 959169.08 | ... AM52: =Z52*0.5 -> 684803.84 | AN52: =SUM(AB52:AM52) -> 17782880 | AW52: расчет | BA52: =X52-AX52 -> 3236249.1 | BB52: =Y52-AY52 -> 1928920.1 | BC52: =Z52-AZ52 -> 1369607.7
A53: =CONCATENATE(B53,C53,D53,E53,F53,G53,H53,I53,J53,K53,L53,M53,N53) -> СКБСЖРозницаWMНон-лайфСКБЖНСЖ_СИВ_ДМСCiti KidsЕдиновременнаяНовый | B53: СКБСЖ | C53: =IFERROR(VLOOKUP(D53,Каналы!$B:$C,2,0),"") -> Розница | D53: WM | H53: Нон-лайф | I53: СКБЖ | K53: НСЖ_СИВ_ДМС | L53: Citi Kids | M53: Единовременная | N53: Новый | O53: 0 | P53: 0 | Q53: 0 | R53: 0 | S53: 0 | T53: 0 | U53: 0 | V53: 0 | W53: 0 | AA53: =SUM(O53:Z53) -> 0 | AN53: =SUM(AB53:AM53) -> 0 | AW53: 0 | BA53: =X53-AX53 -> 0 | BB53: =Y53-AY53 -> 0 | BC53: =Z53-AZ53 -> 0
A54: =CONCATENATE(B54,C54,D54,E54,F54,G54,H54,I54,J54,K54,L54,M54,N54) -> СКБСЖРозницаWMНон-лайфСКБЖНСЖ_СИВ_ДМСCiti KidsРегулярнаяПролонгация | B54: СКБСЖ | C54: =IFERROR(VLOOKUP(D54,Каналы!$B:$C,2,0),"") -> Розница | D54: WM | H54: Нон-лайф | I54: СКБЖ | K54: НСЖ_СИВ_ДМС | L54: Citi Kids | M54: Регулярная | N54: Пролонгация | O54: 0 | P54: 0 | Q54: 0 | R54: 0 | S54: 0 | T54: 0 | U54: 0 | V54: 0 | W54: 0 | AA54: =SUM(O54:Z54) -> 0 | AB54: =O54*0.5 -> 0 | AN54: =SUM(AB54:AM54) -> 0 | AW54: 0 | BA54: =X54-AX54 -> 0 | BB54: =Y54-AY54 -> 0 | BC54: =Z54-AZ54 -> 0
A55: =CONCATENATE(B55,C55,D55,E55,F55,G55,H55,I55,J55,K55,L55,M55,N55) -> СКБСЖРозницаWMНон-лайфСКБЖНСЖ_СИВ_ДМСCiti PremiumЕдиновременнаяНовый | B55: СКБСЖ | C55: =IFERROR(VLOOKUP(D55,Каналы!$B:$C,2,0),"") -> Розница | D55: WM | H55: Нон-лайф | I55: СКБЖ | K55: НСЖ_СИВ_ДМС | L55: Citi Premium | M55: Единовременная | N55: Новый | P55: 0 | V55: 0 | AA55: =SUM(O55:Z55) -> 0 | AN55: =SUM(AB55:AM55) -> 0 | AW55: 0 | BA55: =X55-AX55 -> 0 | BB55: =Y55-AY55 -> 0 | BC55: =Z55-AZ55 -> 0
A56: =CONCATENATE(B56,C56,D56,E56,F56,G56,H56,I56,J56,K56,L56,M56,N56) -> СКБСЖРозницаWMНон-лайфСКБЖНСЖ_СИВ_ДМСCiti PremiumРегулярнаяПролонгация | B56: СКБСЖ | C56: =IFERROR(VLOOKUP(D56,Каналы!$B:$C,2,0),"") -> Розница | D56: WM | H56: Нон-лайф | I56: СКБЖ | K56: НСЖ_СИВ_ДМС | L56: Citi Premium | M56: Регулярная | N56: Пролонгация | O56: 0 | P56: 0 | Q56: 0 | R56: 0 | S56: 0 | T56: 0 | U56: 0 | V56: 0 | W56: 0 | AA56: =SUM(O56:Z56) -> 0 | AB56: =O56*0.5 -> 0 | AN56: =SUM(AB56:AM56) -> 0 | AW56: 0 | BA56: =X56-AX56 -> 0 | BB56: =Y56-AY56 -> 0 | BC56: =Z56-AZ56 -> 0
A57: =CONCATENATE(B57,C57,D57,E57,F57,G57,H57,I57,J57,K57,L57,M57,N57) -> СКБСЖРозницаWMНон-лайфСКБЖНСЖ_СИВ_ДМСПрочее (СИВ)ЕдиновременнаяНовый | B57: СКБСЖ | C57: =IFERROR(VLOOKUP(D57,Каналы!$B:$C,2,0),"") -> Розница | D57: WM | H57: Нон-лайф | I57: СКБЖ | K57: НСЖ_СИВ_ДМС | L57: Прочее (СИВ) | M57: Единовременная | N57: Новый | P57: 0 | AA57: =SUM(O57:Z57) -> 0 | AN57: =SUM(AB57:AM57) -> 0 | AW57: 0 | BA57: =X57-AX57 -> 0 | BB57: =Y57-AY57 -> 0 | BC57: =Z57-AZ57 -> 0
A58: =CONCATENATE(B58,C58,D58,E58,F58,G58,H58,I58,J58,K58,L58,M58,N58) -> СКБСЖРозницаWMНон-лайфСКБЖНСЖ_СИВ_ДМСПрочее (СИВ)РегулярнаяПролонгация | B58: СКБСЖ | C58: =IFERROR(VLOOKUP(D58,Каналы!$B:$C,2,0),"") -> Розница | D58: WM | H58: Нон-лайф | I58: СКБЖ | K58: НСЖ_СИВ_ДМС | L58: Прочее (СИВ) | M58: Регулярная | N58: Пролонгация | O58: 0 | P58: 235425.91 | Q58: 163893.59 | R58: 320813.72 | S58: 106642.95 | T58: 198399.49 | U58: 0 | V58: 118542.16 | W58: 184080.93 | X58: 78261.795 | Y58: 114720.84 | Z58: 186715.59 | AA58: =SUM(O58:Z58) -> 1707497 | AB58: =O58*0.5 -> 0 | AN58: =SUM(AB58:AM58) -> 0 | AW58: расчет | BA58: =X58-AX58 -> 78261.795 | BB58: =Y58-AY58 -> 114720.84 | BC58: =Z58-AZ58 -> 186715.59
A59: =CONCATENATE(B59,C59,D59,E59,F59,G59,H59,I59,J59,K59,L59,M59,N59) -> СКБСЖРозницаWMНон-лайфСКБЖНСЖ_СИВ_ДМССтабильный курсЕдиновременнаяНовый | B59: СКБСЖ | C59: =IFERROR(VLOOKUP(D59,Каналы!$B:$C,2,0),"") -> Розница | D59: WM | H59: Нон-лайф | I59: СКБЖ | K59: НСЖ_СИВ_ДМС | L59: Стабильный курс | M59: Единовременная | N59: Новый | O59: 0 | P59: 559581.13 | Q59: 0 | R59: 50823.53 | S59: 0 | T59: 0 | U59: 134664.36 | V59: 127073.53 | W59: 0 | X59: 137004.55 | Y59: 72950.585 | Z59: 0 | AA59: =SUM(O59:Z59) -> 1082097.7 | AN59: =SUM(AB59:AM59) -> 0 | AW59: расчет | BA59: =X59-AX59 -> 137004.55 | BB59: =Y59-AY59 -> 72950.585 | BC59: =Z59-AZ59 -> 0
A60: =CONCATENATE(B60,C60,D60,E60,F60,G60,H60,I60,J60,K60,L60,M60,N60) -> СКБСЖРозницаWMНон-лайфСКБЖНСЖ_СИВ_ДМССтабильный курсРегулярнаяНовый | B60: СКБСЖ | C60: =IFERROR(VLOOKUP(D60,Каналы!$B:$C,2,0),"") -> Розница | D60: WM | H60: Нон-лайф | I60: СКБЖ | K60: НСЖ_СИВ_ДМС | L60: Стабильный курс | M60: Регулярная | N60: Новый | O60: 165899.1 | P60: 50650.28 | R60: 248932.34 | S60: 56580.31 | T60: 123690.05 | U60: 0 | V60: 0 | AA60: =SUM(O60:Z60) -> 645752.08 | AN60: =SUM(AB60:AM60) -> 0 | AW60: расчет | BA60: =X60-AX60 -> 0 | BB60: =Y60-AY60 -> 0 | BC60: =Z60-AZ60 -> 0
A61: =CONCATENATE(B61,C61,D61,E61,F61,G61,H61,I61,J61,K61,L61,M61,N61) -> СКБСЖРозницаWMНон-лайфСКБЖНСЖ_СИВ_ДМССтабильный курсРегулярнаяПролонгация | B61: СКБСЖ | C61: =IFERROR(VLOOKUP(D61,Каналы!$B:$C,2,0),"") -> Розница | D61: WM | H61: Нон-лайф | I61: СКБЖ | K61: НСЖ_СИВ_ДМС | L61: Стабильный курс | M61: Регулярная | N61: Пролонгация | P61: 0 | Q61: 93481.26 | R61: 0 | S61: 0 | T61: 288949.27 | U61: 0 | V61: 378608.51 | W61: 311142.25 | X61: 0 | Y61: 7084933.5 | Z61: 15103804 | AA61: =SUM(O61:Z61) -> 23260918 | AB61: =O61*0.5 -> 0 | AN61: =SUM(AB61:AM61) -> 0 | AW61: расчет | BA61: =X61-AX61 -> 0 | BB61: =Y61-AY61 -> 7084933.5 | BC61: =Z61-AZ61 -> 15103804
A62: =CONCATENATE(B62,C62,D62,E62,F62,G62,H62,I62,J62,K62,L62,M62,N62) -> СКБСЖРозницаWMНон-лайфСКБЖНСЖ_СИВ_ДМССила процентаЕдиновременнаяНовый | B62: СКБСЖ | C62: =IFERROR(VLOOKUP(D62,Каналы!$B:$C,2,0),"") -> Розница | D62: WM | H62: Нон-лайф | I62: СКБЖ | K62: НСЖ_СИВ_ДМС | L62: Сила процента | M62: Единовременная | N62: Новый | V62: 0 | W62: 0 | AA62: =SUM(O62:Z62) -> 0 | AN62: =SUM(AB62:AM62) -> 0 | AW62: 0 | BA62: =X62-AX62 -> 0 | BB62: =Y62-AY62 -> 0 | BC62: =Z62-AZ62 -> 0
A63: =CONCATENATE(B63,C63,D63,E63,F63,G63,H63,I63,J63,K63,L63,M63,N63) -> СКБСЖРозницаWMНон-лайфСКБЖНСЖ_СИВ_НСCiti ComfortРегулярнаяПролонгация | B63: СКБСЖ | C63: =IFERROR(VLOOKUP(D63,Каналы!$B:$C,2,0),"") -> Розница | D63: WM | H63: Нон-лайф | I63: СКБЖ | K63: НСЖ_СИВ_НС | L63: Citi Comfort | M63: Регулярная | N63: Пролонгация | O63: 697642.01 | P63: 677502.23 | Q63: 1442385.4 | R63: 658666.83 | S63: 1339429.3 | T63: 1026118.3 | U63: 1706540.3 | V63: 1115847 | W63: 646942.7 | X63: 1723659.9 | Y63: 1133892 | Z63: 659434.64 | AA63: =SUM(O63:Z63) -> 12828061 | AB63: =O63*0.5 -> 348821.01 | AC63: =P63*0.5 -> 338751.12 | AD63: =Q63*0.5 -> 721192.68 | AE63: =R63*0.5 -> 329333.42 | AF63: =S63*0.5 -> 669714.65 | AG63: =T63*0.5 -> 513059.15 | AH63: =U63*0.5 -> 853270.16 | AI63: =V63*0.5 -> 557923.51 | ... AM63: =Z63*0.5 -> 329717.32 | AN63: =SUM(AB63:AM63) -> 6414030.3 | AW63: расчет | BA63: =X63-AX63 -> 1723659.9 | BB63: =Y63-AY63 -> 1133892 | BC63: =Z63-AZ63 -> 659434.64
A64: =CONCATENATE(B64,C64,D64,E64,F64,G64,H64,I64,J64,K64,L64,M64,N64) -> СКБСЖРозницаWMНон-лайфСКБЖНСЖ_СИВ_НСCiti HealthЕдиновременнаяНовый | B64: СКБСЖ | C64: =IFERROR(VLOOKUP(D64,Каналы!$B:$C,2,0),"") -> Розница | D64: WM | H64: Нон-лайф | I64: СКБЖ | K64: НСЖ_СИВ_НС | L64: Citi Health | M64: Единовременная | N64: Новый | O64: 0 | W64: 0 | AA64: =SUM(O64:Z64) -> 0 | AN64: =SUM(AB64:AM64) -> 0 | AW64: 0 | BA64: =X64-AX64 -> 0 | BB64: =Y64-AY64 -> 0 | BC64: =Z64-AZ64 -> 0
A65: =CONCATENATE(B65,C65,D65,E65,F65,G65,H65,I65,J65,K65,L65,M65,N65) -> СКБСЖРозницаWMНон-лайфСКБЖНСЖ_СИВ_НСCiti HealthРегулярнаяПролонгация | B65: СКБСЖ | C65: =IFERROR(VLOOKUP(D65,Каналы!$B:$C,2,0),"") -> Розница | D65: WM | H65: Нон-лайф | I65: СКБЖ | K65: НСЖ_СИВ_НС | L65: Citi Health | M65: Регулярная | N65: Пролонгация | O65: 0 | P65: 0 | Q65: 0 | R65: 0 | S65: 0 | T65: 0 | U65: 0 | V65: 0 | W65: 0 | AA65: =SUM(O65:Z65) -> 0 | AB65: =O65*0.5 -> 0 | AN65: =SUM(AB65:AM65) -> 0 | AW65: 0 | BA65: =X65-AX65 -> 0 | BB65: =Y65-AY65 -> 0 | BC65: =Z65-AZ65 -> 0
A66: =CONCATENATE(B66,C66,D66,E66,F66,G66,H66,I66,J66,K66,L66,M66,N66) -> СКБСЖРозницаWMНон-лайфСКБЖНСЖ_СИВ_НСCiti KidsЕдиновременнаяНовый | B66: СКБСЖ | C66: =IFERROR(VLOOKUP(D66,Каналы!$B:$C,2,0),"") -> Розница | D66: WM | H66: Нон-лайф | I66: СКБЖ | K66: НСЖ_СИВ_НС | L66: Citi Kids | M66: Единовременная | N66: Новый | O66: 0 | P66: 0 | Q66: 0 | R66: 0 | S66: 0 | T66: 0 | U66: 0 | V66: 0 | W66: 0 | AA66: =SUM(O66:Z66) -> 0 | AN66: =SUM(AB66:AM66) -> 0 | AW66: 0 | BA66: =X66-AX66 -> 0 | BB66: =Y66-AY66 -> 0 | BC66: =Z66-AZ66 -> 0
A67: =CONCATENATE(B67,C67,D67,E67,F67,G67,H67,I67,J67,K67,L67,M67,N67) -> СКБСЖРозницаWMНон-лайфСКБЖНСЖ_СИВ_НСCiti KidsРегулярнаяПролонгация | B67: СКБСЖ | C67: =IFERROR(VLOOKUP(D67,Каналы!$B:$C,2,0),"") -> Розница | D67: WM | H67: Нон-лайф | I67: СКБЖ | K67: НСЖ_СИВ_НС | L67: Citi Kids | M67: Регулярная | N67: Пролонгация | O67: 120954.24 | P67: 211945.97 | Q67: 316812.59 | R67: 203266.76 | S67: 321246.91 | T67: 349447.42 | U67: 218992.66 | V67: 248166.39 | W67: 707296.64 | X67: 22460.121 | Y67: 249254.76 | Z67: 705933.25 | AA67: =SUM(O67:Z67) -> 3675777.7 | AB67: =O67*0.5 -> 60477.12 | AC67: =P67*0.5 -> 105972.99 | AD67: =Q67*0.5 -> 158406.29 | AE67: =R67*0.5 -> 101633.38 | AF67: =S67*0.5 -> 160623.45 | AG67: =T67*0.5 -> 174723.71 | AH67: =U67*0.5 -> 109496.33 | AI67: =V67*0.5 -> 124083.2 | ... AM67: =Z67*0.5 -> 352966.63 | AN67: =SUM(AB67:AM67) -> 1837888.9 | AW67: расчет | BA67: =X67-AX67 -> 22460.121 | BB67: =Y67-AY67 -> 249254.76 | BC67: =Z67-AZ67 -> 705933.25
A68: =CONCATENATE(B68,C68,D68,E68,F68,G68,H68,I68,J68,K68,L68,M68,N68) -> СКБСЖРозницаWMНон-лайфСКБЖНСЖ_СИВ_НСCiti PremiumЕдиновременнаяНовый | B68: СКБСЖ | C68: =IFERROR(VLOOKUP(D68,Каналы!$B:$C,2,0),"") -> Розница | D68: WM | H68: Нон-лайф | I68: СКБЖ | K68: НСЖ_СИВ_НС | L68: Citi Premium | M68: Единовременная | N68: Новый | P68: 0 | V68: 0 | AA68: =SUM(O68:Z68) -> 0 | AN68: =SUM(AB68:AM68) -> 0 | AW68: 0 | BA68: =X68-AX68 -> 0 | BB68: =Y68-AY68 -> 0 | BC68: =Z68-AZ68 -> 0
A69: =CONCATENATE(B69,C69,D69,E69,F69,G69,H69,I69,J69,K69,L69,M69,N69) -> СКБСЖРозницаWMНон-лайфСКБЖНСЖ_СИВ_НСCiti PremiumРегулярнаяПролонгация | B69: СКБСЖ | C69: =IFERROR(VLOOKUP(D69,Каналы!$B:$C,2,0),"") -> Розница | D69: WM | H69: Нон-лайф | I69: СКБЖ | K69: НСЖ_СИВ_НС | L69: Citi Premium | M69: Регулярная | N69: Пролонгация | O69: 711068.82 | P69: 771552.7 | Q69: 348038.06 | R69: 937711.01 | S69: 882565.49 | T69: 925882.35 | U69: 831597.06 | V69: 698690.93 | W69: 880706.69 | X69: 829135.32 | Y69: 698906.75 | Z69: 879411.95 | AA69: =SUM(O69:Z69) -> 9395267.1 | AB69: =O69*0.5 -> 355534.41 | AC69: =P69*0.5 -> 385776.35 | AD69: =Q69*0.5 -> 174019.03 | AE69: =R69*0.5 -> 468855.5 | AF69: =S69*0.5 -> 441282.74 | AG69: =T69*0.5 -> 462941.17 | AH69: =U69*0.5 -> 415798.53 | AI69: =V69*0.5 -> 349345.47 | ... AM69: =Z69*0.5 -> 439705.97 | AN69: =SUM(AB69:AM69) -> 4697633.6 | AW69: расчет | BA69: =X69-AX69 -> 829135.32 | BB69: =Y69-AY69 -> 698906.75 | BC69: =Z69-AZ69 -> 879411.95
A70: =CONCATENATE(B70,C70,D70,E70,F70,G70,H70,I70,J70,K70,L70,M70,N70) -> СКБСЖРозницаWMНон-лайфСКБЖНСЖ_СИВ_НСПрочее (СИВ)ЕдиновременнаяНовый | B70: СКБСЖ | C70: =IFERROR(VLOOKUP(D70,Каналы!$B:$C,2,0),"") -> Розница | D70: WM | H70: Нон-лайф | I70: СКБЖ | K70: НСЖ_СИВ_НС | L70: Прочее (СИВ) | M70: Единовременная | N70: Новый | P70: 0 | AA70: =SUM(O70:Z70) -> 0 | AN70: =SUM(AB70:AM70) -> 0 | AW70: 0 | BA70: =X70-AX70 -> 0 | BB70: =Y70-AY70 -> 0 | BC70: =Z70-AZ70 -> 0
A71: =CONCATENATE(B71,C71,D71,E71,F71,G71,H71,I71,J71,K71,L71,M71,N71) -> СКБСЖРозницаWMНон-лайфСКБЖНСЖ_СИВ_НСПрочее (СИВ)РегулярнаяПролонгация | B71: СКБСЖ | C71: =IFERROR(VLOOKUP(D71,Каналы!$B:$C,2,0),"") -> Розница | D71: WM | H71: Нон-лайф | I71: СКБЖ | K71: НСЖ_СИВ_НС | L71: Прочее (СИВ) | M71: Регулярная | N71: Пролонгация | O71: 26113.13 | P71: 219939.05 | Q71: 23053.53 | R71: 25087.45 | S71: 24886.85 | T71: 23328.27 | U71: 45723.15 | V71: 20359.39 | W71: 60776.73 | X71: 45079.556 | Y71: 19703.085 | Z71: 61646.596 | AA71: =SUM(O71:Z71) -> 595696.79 | AB71: =O71*0.5 -> 13056.565 | AC71: =P71*0.5 -> 109969.52 | AD71: =Q71*0.5 -> 11526.765 | AE71: =R71*0.5 -> 12543.725 | AF71: =S71*0.5 -> 12443.425 | AG71: =T71*0.5 -> 11664.135 | AH71: =U71*0.5 -> 22861.575 | AI71: =V71*0.5 -> 10179.695 | ... AM71: =Z71*0.5 -> 30823.298 | AN71: =SUM(AB71:AM71) -> 297848.39 | AW71: расчет | BA71: =X71-AX71 -> 45079.556 | BB71: =Y71-AY71 -> 19703.085 | BC71: =Z71-AZ71 -> 61646.596
A72: =CONCATENATE(B72,C72,D72,E72,F72,G72,H72,I72,J72,K72,L72,M72,N72) -> СКБСЖРозницаWMНон-лайфСКБЖНСЖ_СИВ_НССтабильный курсЕдиновременнаяНовый | B72: СКБСЖ | C72: =IFERROR(VLOOKUP(D72,Каналы!$B:$C,2,0),"") -> Розница | D72: WM | H72: Нон-лайф | I72: СКБЖ | K72: НСЖ_СИВ_НС | L72: Стабильный курс | M72: Единовременная | N72: Новый | O72: 72027.84 | P72: 170398.84 | Q72: 440943.11 | R72: 280814.12 | S72: 259822.4 | T72: 415859.17 | U72: 177642.74 | V72: 739912.79 | W72: 52904.77 | X72: 180729.81 | Y72: 424770.37 | Z72: 178905.99 | AA72: =SUM(O72:Z72) -> 3394731.9 | AN72: =SUM(AB72:AM72) -> 0 | AW72: расчет | BA72: =X72-AX72 -> 180729.81 | BB72: =Y72-AY72 -> 424770.37 | BC72: =Z72-AZ72 -> 178905.99
A73: =CONCATENATE(B73,C73,D73,E73,F73,G73,H73,I73,J73,K73,L73,M73,N73) -> СКБСЖРозницаWMНон-лайфСКБЖНСЖ_СИВ_НССтабильный курсРегулярнаяНовый | B73: СКБСЖ | C73: =IFERROR(VLOOKUP(D73,Каналы!$B:$C,2,0),"") -> Розница | D73: WM | H73: Нон-лайф | I73: СКБЖ | K73: НСЖ_СИВ_НС | L73: Стабильный курс | M73: Регулярная | N73: Новый | O73: 2185.64 | P73: 9965.79 | R73: 4084.37 | S73: 2473.14 | T73: 887.7 | U73: 2064.27 | V73: 251.74 | X73: 0 | Y73: 0 | Z73: 0 | AA73: =SUM(O73:Z73) -> 21912.65 | AN73: =SUM(AB73:AM73) -> 0 | AW73: расчет | BA73: =X73-AX73 -> 0 | BB73: =Y73-AY73 -> 0 | BC73: =Z73-AZ73 -> 0
A74: =CONCATENATE(B74,C74,D74,E74,F74,G74,H74,I74,J74,K74,L74,M74,N74) -> СКБСЖРозницаWMНон-лайфСКБЖНСЖ_СИВ_НССтабильный курсРегулярнаяПролонгация | B74: СКБСЖ | C74: =IFERROR(VLOOKUP(D74,Каналы!$B:$C,2,0),"") -> Розница | D74: WM | H74: Нон-лайф | I74: СКБЖ | K74: НСЖ_СИВ_НС | L74: Стабильный курс | M74: Регулярная | N74: Пролонгация | P74: 15973.06 | Q74: 6372.63 | R74: 3613.16 | S74: 10069.76 | T74: 9340.03 | U74: 14510 | V74: 19850.76 | W74: 17414.94 | X74: 410384.21 | Y74: 371468.97 | Z74: 845374.85 | AA74: =SUM(O74:Z74) -> 1724372.4 | AB74: =O74*0.5 -> 0 | AN74: =SUM(AB74:AM74) -> 0 | AW74: расчет | BA74: =X74-AX74 -> 410384.21 | BB74: =Y74-AY74 -> 371468.97 | BC74: =Z74-AZ74 -> 845374.85
A75: =CONCATENATE(B75,C75,D75,E75,F75,G75,H75,I75,J75,K75,L75,M75,N75) -> СКБСЖРозницаWMНон-лайфСКБЖНСЖ_СИВ_НССила процентаЕдиновременнаяНовый | B75: СКБСЖ | C75: =IFERROR(VLOOKUP(D75,Каналы!$B:$C,2,0),"") -> Розница | D75: WM | H75: Нон-лайф | I75: СКБЖ | K75: НСЖ_СИВ_НС | L75: Сила процента | M75: Единовременная | N75: Новый | V75: 17791.81 | W75: 27122.42 | X75: 281460.42 | Y75: 169444.85 | Z75: 149204.93 | AA75: =SUM(O75:Z75) -> 645024.43 | AN75: =SUM(AB75:AM75) -> 0 | AW75: расчет | BA75: =X75-AX75 -> 281460.42 | BB75: =Y75-AY75 -> 169444.85 | BC75: =Z75-AZ75 -> 149204.93
A76: =CONCATENATE(B76,C76,D76,E76,F76,G76,H76,I76,J76,K76,L76,M76,N76) -> СКБСЖУралсиб_УралсибЛайфУралсибИСЖ_УралсибВерное решениеЕдиновременнаяНовый | B76: СКБСЖ | C76: =IFERROR(VLOOKUP(D76,Каналы!$B:$C,2,0),"") -> Уралсиб_ | D76: Уралсиб | H76: Лайф | I76: Уралсиб | K76: ИСЖ_Уралсиб | L76: Верное решение | M76: Единовременная | N76: Новый | O76: 45539490 | P76: 50830397 | Q76: 30800558 | R76: 44427530 | S76: 32141234 | T76: 30905468 | U76: 11352350 | V76: -5019691 | W76: 1500000 | X76: 3500000 | Y76: 18000000 | Z76: 18000000 | AA76: =SUM(O76:Z76) -> 2.8197734e+08 | AB76: 0 | AC76: 0 | AD76: 0 | AE76: 0 | AF76: 0 | AG76: 0 | AH76: 0 | AI76: 0 | AJ76: 0 | AK76: 0 | AL76: 0 | AM76: 0 | AN76: =SUM(AB76:AM76) -> 0 | AW76: ок | AX76: 3500000 | AY76: 18000000 | AZ76: 18000000 | BA76: =X76-AX76 -> 0 | BB76: =Y76-AY76 -> 0 | BC76: =Z76-AZ76 -> 0
A77: =CONCATENATE(B77,C77,D77,E77,F77,G77,H77,I77,J77,K77,L77,M77,N77) -> СКБСЖУралсиб_УралсибЛайфУралсибНСЖ_УралсибЛегкий стартРегулярнаяНовый | B77: СКБСЖ | C77: =IFERROR(VLOOKUP(D77,Каналы!$B:$C,2,0),"") -> Уралсиб_ | D77: Уралсиб | H77: Лайф | I77: Уралсиб | K77: НСЖ_Уралсиб | L77: Легкий старт | M77: Регулярная | N77: Новый | O77: 5161000 | P77: 5430000 | Q77: 30567141 | R77: 182645099 | S77: 128578411 | T77: 170568819 | U77: 376180767 | V77: 301890939 | W77: 243518456 | X77: 200000000 | Y77: 100000000 | Z77: 100000000 | AA77: =SUM(O77:Z77) -> 1844540632 | AB77: 35000000 | AC77: 45000000 | AD77: 100000000 | AE77: 100000000 | AF77: 50000000 | AG77: 50000000 | AH77: 50000000 | AI77: 50000000 | AJ77: 50000000 | AK77: 50000000 | AL77: 50000000 | AM77: 50000000 | AN77: =SUM(AB77:AM77) -> 680000000 | AW77: ок кроме октября (окт по факту) | AX77: 100000000 | AY77: 100000000 | AZ77: 100000000 | BA77: =X77-AX77 -> 100000000 | BB77: =Y77-AY77 -> 0 | BC77: =Z77-AZ77 -> 0
A78: =CONCATENATE(B78,C78,D78,E78,F78,G78,H78,I78,J78,K78,L78,M78,N78) -> СКБСЖУралсиб_УралсибЛайфУралсибНСЖ_УралсибЛегкий стартРегулярнаяПролонгация | B78: СКБСЖ | C78: =IFERROR(VLOOKUP(D78,Каналы!$B:$C,2,0),"") -> Уралсиб_ | D78: Уралсиб | H78: Лайф | I78: Уралсиб | K78: НСЖ_Уралсиб | L78: Легкий старт | M78: Регулярная | N78: Пролонгация | O78: 500000 | P78: 13959000 | Q78: 3857000 | R78: 8646000 | S78: 8308245 | T78: 19265000 | U78: 6968500 | V78: 20081500 | W78: 15880000 | X78: 14600000 | Y78: 14600000 | Z78: 14600000 | AA78: =SUM(O78:Z78) -> 141265245 | AB78: =O78*0.7 -> 350000 | AC78: =P78*0.7 -> 9771300 | AD78: =Q78*0.7 -> 2699900 | AE78: =R78*0.7 -> 6052200 | AF78: =S78*0.7 -> 5815771.5 | AG78: =T78*0.7 -> 13485500 | AH78: =U78*0.7 -> 4877950 | AI78: =V78*0.7 -> 14057050 | ... AM78: =Z78*0.7 -> 10220000 | AN78: =SUM(AB78:AM78) -> 98885672 | AW78: подняли до уровня 3 кв | BA78: =X78-AX78 -> 14600000 | BB78: =Y78-AY78 -> 14600000 | BC78: =Z78-AZ78 -> 14600000
A79: =CONCATENATE(B79,C79,D79,E79,F79,G79,H79,I79,J79,K79,L79,M79,N79) -> СКБСЖУралсиб_УралсибЛайфУралсибНСЖ_УралсибПрочее (Уралсиб)ЕдиновременнаяНовый | B79: СКБСЖ | C79: =IFERROR(VLOOKUP(D79,Каналы!$B:$C,2,0),"") -> Уралсиб_ | D79: Уралсиб | H79: Лайф | I79: Уралсиб | K79: НСЖ_Уралсиб | L79: Прочее (Уралсиб) | M79: Единовременная | N79: Новый | V79: -100000 | AA79: =SUM(O79:Z79) -> -100000 | AN79: =SUM(AB79:AM79) -> 0 | AW79: 0 | BA79: =X79-AX79 -> 0 | BB79: =Y79-AY79 -> 0 | BC79: =Z79-AZ79 -> 0
A80: =CONCATENATE(B80,C80,D80,E80,F80,G80,H80,I80,J80,K80,L80,M80,N80) -> СКБСЖУралсиб_УралсибЛайфУралсибНСЖ_УралсибПрочее (Уралсиб)РегулярнаяПролонгация | B80: СКБСЖ | C80: =IFERROR(VLOOKUP(D80,Каналы!$B:$C,2,0),"") -> Уралсиб_ | D80: Уралсиб | H80: Лайф | I80: Уралсиб | K80: НСЖ_Уралсиб | L80: Прочее (Уралсиб) | M80: Регулярная | N80: Пролонгация | O80: 4102937.6 | P80: 9117569.7 | Q80: 7554227 | R80: 4823647.2 | S80: 3818611.6 | T80: 7382927 | U80: 4916093.7 | V80: 7302852.2 | W80: 8463386.4 | X80: 5000000 | Y80: 7300000 | Z80: 8500000 | AA80: =SUM(O80:Z80) -> 78282252 | AB80: =O80*0.7 -> 2872056.3 | AC80: =P80*0.7 -> 6382298.8 | AD80: =Q80*0.7 -> 5287958.9 | AE80: =R80*0.7 -> 3376553.1 | AF80: =S80*0.7 -> 2673028.1 | AG80: =T80*0.7 -> 5168048.9 | AH80: =U80*0.7 -> 3441265.6 | AI80: =V80*0.7 -> 5111996.5 | ... AM80: =Z80*0.7 -> 5950000 | AN80: =SUM(AB80:AM80) -> 54797577 | AW80: подняли до уровня 3 кв | BA80: =X80-AX80 -> 5000000 | BB80: =Y80-AY80 -> 7300000 | BC80: =Z80-AZ80 -> 8500000
A81: =CONCATENATE(B81,C81,D81,E81,F81,G81,H81,I81,J81,K81,L81,M81,N81) -> СКБСЖУралсиб_УралсибЛайфУралсибНСЖ_УралсибСтабильный доходЕдиновременнаяНовый | B81: СКБСЖ | C81: =IFERROR(VLOOKUP(D81,Каналы!$B:$C,2,0),"") -> Уралсиб_ | D81: Уралсиб | H81: Лайф | I81: Уралсиб | K81: НСЖ_Уралсиб | L81: Стабильный доход | M81: Единовременная | N81: Новый | O81: 184234362 | P81: 71951023 | Q81: 41510107 | R81: 31571337 | S81: 42271839 | T81: 59661440 | U81: 77644727 | V81: 36824903 | W81: 40012536 | X81: 50000000 | Y81: 50000000 | Z81: 50000000 | AA81: =SUM(O81:Z81) -> 735682274 | AB81: 30000000 | AC81: 40000000 | AD81: 40000000 | AE81: 40000000 | AF81: 30000000 | AG81: 40000000 | AH81: 40000000 | AI81: 40000000 | AJ81: 50000000 | AK81: 50000000 | AL81: 50000000 | AM81: 50000000 | AN81: =SUM(AB81:AM81) -> 500000000 | AW81: подняли до уровня 3 кв | AX81: 40000000 | AY81: 40000000 | AZ81: 40000000 | BA81: =X81-AX81 -> 10000000 | BB81: =Y81-AY81 -> 10000000 | BC81: =Z81-AZ81 -> 10000000
A82: =CONCATENATE(B82,C82,D82,E82,F82,G82,H82,I82,J82,K82,L82,M82,N82) -> СКБСЖУралсиб_УралсибЛайфУралсибНСЖ_УралсибСтабильный доходРегулярнаяПролонгация | B82: СКБСЖ | C82: =IFERROR(VLOOKUP(D82,Каналы!$B:$C,2,0),"") -> Уралсиб_ | D82: Уралсиб | H82: Лайф | I82: Уралсиб | K82: НСЖ_Уралсиб | L82: Стабильный доход | M82: Регулярная | N82: Пролонгация | AA82: =SUM(O82:Z82) -> 0 | AN82: =SUM(AB82:AM82) -> 0 | AW82: 0 | BA82: =X82-AX82 -> 0 | BB82: =Y82-AY82 -> 0 | BC82: =Z82-AZ82 -> 0
A83: =CONCATENATE(B83,C83,D83,E83,F83,G83,H83,I83,J83,K83,L83,M83,N83) -> СКБСЖУралсиб_УралсибНон-лайфУралсибКСЖ_УралсибКСЖ (Уралсиб)ЕдиновременнаяНовый | B83: СКБСЖ | C83: =IFERROR(VLOOKUP(D83,Каналы!$B:$C,2,0),"") -> Уралсиб_ | D83: Уралсиб | H83: Нон-лайф | I83: Уралсиб | K83: КСЖ_Уралсиб | L83: КСЖ (Уралсиб) | M83: Единовременная | N83: Новый | O83: 29598275 | P83: 43318615 | Q83: 41185353 | R83: 31711438 | S83: 37241321 | T83: 39942753 | U83: 31785968 | V83: 47125238 | W83: 37955582 | X83: 40000000 | Y83: 40000000 | Z83: 40000000 | AA83: =SUM(O83:Z83) -> 4.5986454e+08 | AB83: 5000000 | AC83: 7000000 | AD83: 10000000 | AE83: 10000000 | AF83: 10000000 | AG83: 10000000 | AH83: 10000000 | AI83: 10000000 | AJ83: 10000000 | AK83: 10000000 | AL83: 10000000 | AM83: 10000000 | AN83: =SUM(AB83:AM83) -> 112000000 | AW83: подняли до уровня 3 кв | AX83: 6000000 | AY83: 6000000 | AZ83: 6000000 | BA83: =X83-AX83 -> 34000000 | BB83: =Y83-AY83 -> 34000000 | BC83: =Z83-AZ83 -> 34000000
A84: =CONCATENATE(B84,C84,D84,E84,F84,G84,H84,I84,J84,K84,L84,M84,N84) -> СКБСЖУралсиб_УралсибНон-лайфУралсибКСЖ_УралсибКСЖ (Уралсиб)РегулярнаяНовый | B84: СКБСЖ | C84: =IFERROR(VLOOKUP(D84,Каналы!$B:$C,2,0),"") -> Уралсиб_ | D84: Уралсиб | H84: Нон-лайф | I84: Уралсиб | K84: КСЖ_Уралсиб | L84: КСЖ (Уралсиб) | M84: Регулярная | N84: Новый | O84: -396087.61 | P84: -465260.8 | Q84: -680380.12 | R84: -412377.15 | S84: -427468.39 | T84: -333015.81 | U84: -220919.52 | V84: -332936.25 | W84: -340227.61 | AA84: =SUM(O84:Z84) -> -3608673.3 | AN84: =SUM(AB84:AM84) -> 0 | AW84: 0 | BA84: =X84-AX84 -> 0 | BB84: =Y84-AY84 -> 0 | BC84: =Z84-AZ84 -> 0
A85: =CONCATENATE(B85,C85,D85,E85,F85,G85,H85,I85,J85,K85,L85,M85,N85) -> СКБСЖУралсиб_УралсибНон-лайфУралсибКСЖ_УралсибКСЖ (Уралсиб)РегулярнаяПролонгация | B85: СКБСЖ | C85: =IFERROR(VLOOKUP(D85,Каналы!$B:$C,2,0),"") -> Уралсиб_ | D85: Уралсиб | H85: Нон-лайф | I85: Уралсиб | K85: КСЖ_Уралсиб | L85: КСЖ (Уралсиб) | M85: Регулярная | N85: Пролонгация | X85: 0 | Y85: 0 | Z85: 0 | AA85: =SUM(O85:Z85) -> 0 | AN85: =SUM(AB85:AM85) -> 0 | AW85: удалили минус | AX85: -12652533 | AY85: -12488361 | AZ85: -12294951 | BA85: =X85-AX85 -> 12652533 | BB85: =Y85-AY85 -> 12488361 | BC85: =Z85-AZ85 -> 12294951
A86: =CONCATENATE(B86,C86,D86,E86,F86,G86,H86,I86,J86,K86,L86,M86,N86) -> СКБСЖУралсиб_УралсибНон-лайфУралсибКСЖ_УралсибПрочее (Уралсиб)ЕдиновременнаяНовый | B86: СКБСЖ | C86: =IFERROR(VLOOKUP(D86,Каналы!$B:$C,2,0),"") -> Уралсиб_ | D86: Уралсиб | H86: Нон-лайф | I86: Уралсиб | K86: КСЖ_Уралсиб | L86: Прочее (Уралсиб) | M86: Единовременная | N86: Новый | O86: 3344922 | P86: 3374072.4 | Q86: 3535166.6 | R86: 3550980.3 | S86: 3910022.6 | T86: 3994494 | U86: 4234945.3 | V86: 4395425.1 | W86: 4066721.2 | X86: 4000000 | Y86: 4000000 | Z86: 4000000 | AA86: =SUM(O86:Z86) -> 46406750 | AB86: 3000000 | AC86: 3000000 | AD86: 3500000 | AE86: 3000000 | AF86: 3000000 | AG86: 3500000 | AH86: 3500000 | AI86: 3500000 | AJ86: 4000000 | AK86: 4000000 | AL86: 4000000 | AM86: 4000000 | AN86: =SUM(AB86:AM86) -> 42000000 | AW86: подняли до уровня 3 кв | AX86: 3000000 | AY86: 3000000 | AZ86: 3000000 | BA86: =X86-AX86 -> 1000000 | BB86: =Y86-AY86 -> 1000000 | BC86: =Z86-AZ86 -> 1000000
A87: =CONCATENATE(B87,C87,D87,E87,F87,G87,H87,I87,J87,K87,L87,M87,N87) -> СКБСЖУралсиб_УралсибНон-лайфУралсибПрочее_УралсибПрочее (Уралсиб)РегулярнаяПролонгация | B87: СКБСЖ | C87: =IFERROR(VLOOKUP(D87,Каналы!$B:$C,2,0),"") -> Уралсиб_ | D87: Уралсиб | H87: Нон-лайф | I87: Уралсиб | K87: Прочее_Уралсиб | L87: Прочее (Уралсиб) | M87: Регулярная | N87: Пролонгация | O87: 5914 | P87: 18703.26 | Q87: 21062 | R87: 9033 | S87: -4998 | T87: 8023 | U87: 7745.66 | V87: 7951.42 | W87: 7546.99 | X87: 8000 | Y87: 8000 | Z87: 8000 | AA87: =SUM(O87:Z87) -> 104981.33 | AB87: =O87*0.6 -> 3548.4 | AC87: =P87*0.6 -> 11221.956 | AD87: =Q87*0.6 -> 12637.2 | AE87: =R87*0.6 -> 5419.8 | AF87: =S87*0.6 -> -2998.8 | AG87: =T87*0.6 -> 4813.8 | AH87: =U87*0.6 -> 4647.396 | AI87: =V87*0.6 -> 4770.852 | ... AM87: =Z87*0.6 -> 4800 | AN87: =SUM(AB87:AM87) -> 62988.798 | AW87: подняли до уровня 3 кв | BA87: =X87-AX87 -> 8000 | BB87: =Y87-AY87 -> 8000 | BC87: =Z87-AZ87 -> 8000
A88: =CONCATENATE(B88,C88,D88,E88,F88,G88,H88,I88,J88,K88,L88,M88,N88) -> СКБСЖ | B88: СКБСЖ | C88: =IFERROR(VLOOKUP(D88,Каналы!$B:$C,2,0),"") | E88: =IFERROR(VLOOKUP(D88,Каналы!$B:$D,3,0),"") | H88: =IFERROR(VLOOKUP(K88,ЛБ!$C:$E,3,0),"") | AA88: =SUM(O88:Z88) -> 0 | AN88: =SUM(AB88:AM88) -> 0
A89: =CONCATENATE(B89,C89,D89,E89,F89,G89,H89,I89,J89,K89,L89,M89,N89) -> СКБСЖ | B89: СКБСЖ | C89: =IFERROR(VLOOKUP(D89,Каналы!$B:$C,2,0),"") | E89: =IFERROR(VLOOKUP(D89,Каналы!$B:$D,3,0),"") | H89: =IFERROR(VLOOKUP(K89,ЛБ!$C:$E,3,0),"") | AA89: =SUM(O89:Z89) -> 0 | AN89: =SUM(AB89:AM89) -> 0
A90: =CONCATENATE(B90,C90,D90,E90,F90,G90,H90,I90,J90,K90,L90,M90,N90) -> СКБСЖ | B90: СКБСЖ | C90: =IFERROR(VLOOKUP(D90,Каналы!$B:$C,2,0),"") | E90: =IFERROR(VLOOKUP(D90,Каналы!$B:$D,3,0),"") | H90: =IFERROR(VLOOKUP(K90,ЛБ!$C:$E,3,0),"") | AA90: =SUM(O90:Z90) -> 0 | AN90: =SUM(AB90:AM90) -> 0
A91: =CONCATENATE(B91,C91,D91,E91,F91,G91,H91,I91,J91,K91,L91,M91,N91) -> СКБСЖ | B91: СКБСЖ | C91: =IFERROR(VLOOKUP(D91,Каналы!$B:$C,2,0),"") | E91: =IFERROR(VLOOKUP(D91,Каналы!$B:$D,3,0),"") | H91: =IFERROR(VLOOKUP(K91,ЛБ!$C:$E,3,0),"") | AA91: =SUM(O91:Z91) -> 0 | AN91: =SUM(AB91:AM91) -> 0
A92: =CONCATENATE(B92,C92,D92,E92,F92,G92,H92,I92,J92,K92,L92,M92,N92) -> СКБСЖ | B92: СКБСЖ | C92: =IFERROR(VLOOKUP(D92,Каналы!$B:$C,2,0),"") | E92: =IFERROR(VLOOKUP(D92,Каналы!$B:$D,3,0),"") | H92: =IFERROR(VLOOKUP(K92,ЛБ!$C:$E,3,0),"") | AA92: =SUM(O92:Z92) -> 0 | AN92: =SUM(AB92:AM92) -> 0
A93: =CONCATENATE(B93,C93,D93,E93,F93,G93,H93,I93,J93,K93,L93,M93,N93) -> СКБСЖ | B93: СКБСЖ | C93: =IFERROR(VLOOKUP(D93,Каналы!$B:$C,2,0),"") | E93: =IFERROR(VLOOKUP(D93,Каналы!$B:$D,3,0),"") | H93: =IFERROR(VLOOKUP(K93,ЛБ!$C:$E,3,0),"") | AA93: =SUM(O93:Z93) -> 0 | AN93: =SUM(AB93:AM93) -> 0
A94: =CONCATENATE(B94,C94,D94,E94,F94,G94,H94,I94,J94,K94,L94,M94,N94) -> СКБСЖ | B94: СКБСЖ | C94: =IFERROR(VLOOKUP(D94,Каналы!$B:$C,2,0),"") | E94: =IFERROR(VLOOKUP(D94,Каналы!$B:$D,3,0),"") | H94: =IFERROR(VLOOKUP(K94,ЛБ!$C:$E,3,0),"") | AA94: =SUM(O94:Z94) -> 0 | AN94: =SUM(AB94:AM94) -> 0
A95: =CONCATENATE(B95,C95,D95,E95,F95,G95,H95,I95,J95,K95,L95,M95,N95) -> СКБСЖ | B95: СКБСЖ | C95: =IFERROR(VLOOKUP(D95,Каналы!$B:$C,2,0),"") | E95: =IFERROR(VLOOKUP(D95,Каналы!$B:$D,3,0),"") | H95: =IFERROR(VLOOKUP(K95,ЛБ!$C:$E,3,0),"") | AA95: =SUM(O95:Z95) -> 0 | AN95: =SUM(AB95:AM95) -> 0
A96: =CONCATENATE(B96,C96,D96,E96,F96,G96,H96,I96,J96,K96,L96,M96,N96) -> СКБСЖ | B96: СКБСЖ | C96: =IFERROR(VLOOKUP(D96,Каналы!$B:$C,2,0),"") | E96: =IFERROR(VLOOKUP(D96,Каналы!$B:$D,3,0),"") | H96: =IFERROR(VLOOKUP(K96,ЛБ!$C:$E,3,0),"") | AA96: =SUM(O96:Z96) -> 0 | AN96: =SUM(AB96:AM96) -> 0
A97: =CONCATENATE(B97,C97,D97,E97,F97,G97,H97,I97,J97,K97,L97,M97,N97) -> СКБСЖ | B97: СКБСЖ | C97: =IFERROR(VLOOKUP(D97,Каналы!$B:$C,2,0),"") | E97: =IFERROR(VLOOKUP(D97,Каналы!$B:$D,3,0),"") | H97: =IFERROR(VLOOKUP(K97,ЛБ!$C:$E,3,0),"") | AA97: =SUM(O97:Z97) -> 0 | AN97: =SUM(AB97:AM97) -> 0
A98: =CONCATENATE(B98,C98,D98,E98,F98,G98,H98,I98,J98,K98,L98,M98,N98) -> СКБСЖ | B98: СКБСЖ | C98: =IFERROR(VLOOKUP(D98,Каналы!$B:$C,2,0),"") | E98: =IFERROR(VLOOKUP(D98,Каналы!$B:$D,3,0),"") | H98: =IFERROR(VLOOKUP(K98,ЛБ!$C:$E,3,0),"") | AA98: =SUM(O98:Z98) -> 0 | AN98: =SUM(AB98:AM98) -> 0
A99: =CONCATENATE(B99,C99,D99,E99,F99,G99,H99,I99,J99,K99,L99,M99,N99) -> СКБСЖ | B99: СКБСЖ | C99: =IFERROR(VLOOKUP(D99,Каналы!$B:$C,2,0),"") | E99: =IFERROR(VLOOKUP(D99,Каналы!$B:$D,3,0),"") | H99: =IFERROR(VLOOKUP(K99,ЛБ!$C:$E,3,0),"") | AA99: =SUM(O99:Z99) -> 0 | AN99: =SUM(AB99:AM99) -> 0
... A161: =CONCATENATE(B161,C161,D161,E161,F161,G161,H161,I161,J161,K161,L161,M161,N161) -> СКБСЖ | B161: СКБСЖ | C161: =IFERROR(VLOOKUP(D161,Каналы!$B:$C,2,0),"") | E161: =IFERROR(VLOOKUP(D161,Каналы!$B:$D,3,0),"") | H161: =IFERROR(VLOOKUP(K161,ЛБ!$C:$E,3,0),"") | AA161: =SUM(O161:Z161) -> 0 | AN161: =SUM(AB161:AM161) -> 0

Sheet Свод
A2: Компания | B2: (Все)
A3: L/NL | B3: (Все)
A4: Канал | B4: (Все)
A5: Подканал (код) | B5: (Все)
A6: Регион | B6: (Все)
A7: Новые ТП | B7: (Все)
A8: Периодичность | B8: (Все)
A10: Названия строк | B10: янв.25 | C10: фев.25 | D10: мар.25 | E10: апр.25 | F10: май.25 | G10: июн.25 | H10: июл.25 | I10: авг.25 | J10: сен.25 | K10: окт.25 | L10: ноя.25 | M10: дек.25 | N10: 2025г | O10: янв.26 | P10: фев.26 | Q10: мар.26 | R10: апр.26 | S10: июн.26 | T10: июл.26 | U10: авг.26 | V10: сен.26 | W10: окт.26 | X10: ноя.26 | Y10: дек.26 | Z10: 2026г | AA10: 2026/2025,% | AB10: 2027 | AC10: 2028
A11: Новый | B11: 2.885444e+09 | C11: 4162027677 | D11: 6.6129975e+09 | E11: 1.4393284e+09 | F11: 2.2170324e+09 | G11: 2.2433754e+09 | H11: 2492508689 | I11: 531752537 | J11: 8.660797e+08 | K11: 668500000 | L11: 575500000 | M11: 579000000 | N11: 2.5273546e+10 | Z11: 0 | AA11: 0
A12: ГК | B12: 2.6573514e+08 | C12: 208476422 | D12: 2.2908286e+08 | E12: 411551916 | F12: 250003109 | G12: 2.7807913e+08 | H12: 280055521 | I12: 1.9486686e+08 | J12: 2.7312459e+08 | K12: 270000000 | L12: 220000000 | M12: 220000000 | N12: 3.1009755e+09 | Z12: 0 | AA12: 0
A13: НСЖ_КБ | B13: -10040000 | C13: 12340000 | D13: 13850000 | E13: 1670000 | F13: 5850000 | G13: 10980000 | H13: 21630000 | I13: 8450000 | J13: 9560000 | K13: 5500000 | L13: 5500000 | M13: 9000000 | N13: 94290000 | Z13: 0 | AA13: 0
A14: НП | B14: 2.6297489e+09 | C14: 3941211255 | D14: 6.3700647e+09 | E14: 1.0261065e+09 | F14: 1.9611793e+09 | G14: 1954316259 | H14: 2190823168 | I14: 328435677 | J14: 583395118 | K14: 393000000 | L14: 350000000 | M14: 350000000 | N14: 2.2078281e+10 | Z14: 0 | AA14: 0
A15: СКБЖ | B15: 4.4174977e+08 | C15: 5.7662942e+08 | D15: 6.9973975e+08 | E15: 7.9196842e+08 | F15: 5.73171e+08 | G15: 5.2868715e+08 | H15: 4.1378283e+08 | I15: 6.4790666e+08 | J15: 5.2165516e+08 | K15: 9.4047484e+08 | L15: 6.482189e+08 | M15: 7.1781814e+08 | N15: 7.501802e+09 | Z15: 0 | AA15: 0
A16: ДМС | L16: 24112000 | N16: 24112000 | Z16: 0 | AA16: 0
A17: НС | B17: 4479046.6 | C17: 4127138.3 | D17: 4134853.9 | E17: 5554023.1 | F17: 5644432.9 | G17: 4588408.4 | H17: 4633227 | I17: 4601561.7 | J17: 4227523.7 | K17: 3000000 | L17: 3000000 | M17: 3000000 | N17: 50990216 | Z17: 0 | AA17: 0
A18: Индив.пенсия | H18: 373954.08 | I18: -0.01 | N18: 373954.07 | Z18: 0 | AA18: 0
A19: НСЖ | B19: 3.402138e+08 | C19: 3.4144043e+08 | D19: 4.3791931e+08 | E19: 4.7882016e+08 | F19: 3.8189401e+08 | G19: 2.6874964e+08 | H19: 2.4263785e+08 | I19: 3.7692148e+08 | J19: 3.569011e+08 | K19: 170250000 | L19: 170250000 | M19: 170250000 | N19: 3.7362478e+09 | Z19: 0 | AA19: 0
A20: НСЖ_СИВ | B20: 85774312 | C20: 1.3366469e+08 | D20: 1.838958e+08 | E20: 2.0967148e+08 | F20: 1.6926783e+08 | G20: 2.3968892e+08 | H20: 1.543107e+08 | I20: 2.2398183e+08 | J20: 1.5109356e+08 | K20: 7.6471494e+08 | L20: 4.48347e+08 | M20: 5.4205824e+08 | N20: 3.3064693e+09 | Z20: 0 | AA20: 0
A21: НСЖ_СИВ_ДМС | B21: 1885052.5 | C21: 3749114.3 | D21: 3451018.1 | E21: 7409143.2 | F21: 3730224.5 | G21: 5077303.3 | H21: 3260473.2 | I21: 2542562.4 | J21: 1843966.6 | N21: 32948858 | Z21: 0 | AA21: 0
A22: НСЖ_СИВ_НС | B22: 1629991.7 | C22: 2077277.6 | D22: 2577605.3 | E22: 2113243.7 | F22: 2840493.8 | G22: 2750863.2 | H22: 2997070.2 | I22: 2860870.8 | J22: 2393164.9 | N22: 22240581 | Z22: 0 | AA22: 0
A23: ИСЖ_СИВ | B23: 0 | C23: 85000000 | D23: 60000000 | E23: 80000000 | F23: 0 | G23: 0 | H23: 0 | I23: 30000000 | J23: 0 | N23: 255000000 | Z23: 0 | AA23: 0
A24: ДМС_СИВ | B24: 86937.21 | C24: 0 | D24: 52231.56 | E24: 19451.63 | F24: 48014.15 | G24: 112944.58 | H24: 0 | I24: 38708.2 | J24: -2700.99 | N24: 355586.34 | Z24: 0 | AA24: 0
A25: КСЖ | B25: 7023512.7 | C25: 6057238.2 | D25: 7153090 | E25: 8713385.6 | F25: 9625379.3 | G25: 7747570.3 | H25: 5232509.6 | I25: 6813129.9 | J25: 5080830.4 | K25: 2509900 | L25: 2509900 | M25: 2509900 | N25: 70976346 | Z25: 0 | AA25: 0
A26: КСЖ_СИВ | B26: 462576.4 | C26: 413099.12 | D26: 402065.43 | E26: -430844.41 | F26: -9312.31 | G26: 0 | N26: 837584.23 | Z26: 0 | AA26: 0
A27: НС_СИВ | B27: 194550 | C27: 100440 | D27: 153780 | E27: 98370 | F27: 129930 | G27: -28500 | H27: 337050 | I27: 146520 | J27: 117720 | N27: 1249860 | Z27: 0 | AA27: 0
A28: Уралсиб | B28: 2.7209081e+08 | C28: 1.9753412e+08 | D28: 1.5835023e+08 | E28: 3.0697269e+08 | F28: 2.5583722e+08 | G28: 3.3139591e+08 | H28: 5.1287018e+08 | I28: 4.1217618e+08 | J28: 3.51064e+08 | K28: 1.3984747e+08 | L28: 1.5451164e+08 | M28: 1.5470505e+08 | N28: 3.2473555e+09 | Z28: 0 | AA28: 0
A29: ИСЖ_Уралсиб | B29: 45539490 | C29: 50830397 | D29: 30800558 | E29: 44427530 | F29: 32141234 | G29: 30905468 | H29: 11352350 | I29: -5019691 | J29: 1500000 | K29: 3500000 | L29: 18000000 | M29: 18000000 | N29: 2.8197734e+08 | Z29: 0 | AA29: 0
A30: НСЖ_Уралсиб | B30: 1.939983e+08 | C30: 1.0045759e+08 | D30: 83488475 | E30: 2.2768608e+08 | F30: 1.8297711e+08 | G30: 2.5687819e+08 | H30: 4.6571009e+08 | I30: 3.6600019e+08 | J30: 3.0787438e+08 | K30: 140000000 | L30: 140000000 | M30: 140000000 | N30: 2.6050704e+09 | Z30: 0 | AA30: 0
A31: КСЖ_Уралсиб | B31: 32547109 | C31: 46227427 | D31: 44040140 | E31: 34850041 | F31: 40723875 | G31: 43604231 | H31: 35799994 | I31: 51187726 | J31: 41682075 | K31: -3652532.7 | L31: -3488361.4 | M31: -3294950.5 | N31: 3.6022677e+08 | Z31: 0 | AA31: 0
A32: Прочее_Уралсиб | B32: 5914 | C32: 18703.26 | D32: 21062 | E32: 9033 | F32: -4998 | G32: 8023 | H32: 7745.66 | I32: 7951.42 | J32: 7546.99 | N32: 80981.33 | Z32: 0 | AA32: 0
A33: (пусто) | N33: 0 | Z33: 0 | AA33: #VALUE!
A34: Общий итог | B34: 3.5992846e+09 | C34: 4.9361912e+09 | D34: 7.4710875e+09 | E34: 2.5382695e+09 | F34: 3.0460406e+09 | G34: 3.1034584e+09 | H34: 3.4191617e+09 | I34: 1.5918354e+09 | J34: 1.7387989e+09 | K34: 1.7488223e+09 | L34: 1.3782305e+09 | M34: 1.4515232e+09 | N34: 3.6022704e+10 | Z34: 0 | AA34: 0

Sheet Каналы
B2: СПРАВОЧНИК КАНАЛОВ ПРОДАЖ
B3: Подканал | C3: Канал | D3: Код канала (продукта) | F3: Подканал | G3: Компания | I3: Розница | J3: Уралсиб_ | K3: Агенты | L3: Корпораты | M3: Мульти
B4: Агенты | C4: Агенты | F4: WM | G4: СКБС | I4: WM | J4: Уралсиб | K4: Агенты | L4: Корпораты | M4: Мульти
B5: Брокеры | C5: Агенты | F5: Банкострахование | G5: СКБСЖ | I5: Банкострахование | K5: Брокеры
B6: Корпораты | C6: Корпораты | F6: Розница (прочее) | I6: Розница (прочее)
B7: Мульти | C7: Мульти | F7: Рыночный НС | I7: Рыночный НС
B8: WM | C8: Розница | F8: Уралсиб
B9: Банкострахование | C9: Розница | F9: Агенты
B10: Розница (прочее) | C10: Розница | F10: Брокеры
B11: Рыночный НС | C11: Розница | F11: Корпораты
B12: Уралсиб | C12: Уралсиб_ | F12: Мульти

Sheet Регионы
B1: СПРАВОЧНИК РЕГИОНОВ | F1: СПРАВОЧНИК НОВЫХ ТОЧЕК ПРОДАЖ | I1: !!! Для Добавления Новых Точек продаж в форму Вам необходимо: 1) в столбце "Регион" выбрать из выпадающего списка Регион; 2) далее в столбце "Новые ТП" вести вручную название новой ТП (каждую точку на отдельной строке), по которому будем ее идентифицировать в бюджете. NB! Название должно быть таким же, которое Вы используете в форме "по Бюджету Расходов по этой новой точке.
B2: Регион | C2: признак | F2: Регион | G2: Новые ТП | H2: признак | I2: пояснение к добавлению новой точки
B3: Адыгея | C3: текущие точки | F3: Якутия | G3: Новая ТП_.11 | H3: новые точки
B4: Алтай | C4: текущие точки | H4: новые точки
B5: Анадырь | C5: текущие точки | H5: новые точки
B6: Архангельск | C6: текущие точки | H6: новые точки
B7: Астрахань | C7: текущие точки | H7: новые точки
B8: Барнаул | C8: текущие точки | H8: новые точки
B9: Башкортостан | C9: текущие точки | H9: новые точки
B10: Белгород | C10: текущие точки | H10: новые точки
B11: Биробиджан | C11: текущие точки | H11: новые точки
B12: Благовещенск | C12: текущие точки | H12: новые точки
B13: Брянск | C13: текущие точки | H13: новые точки
B14: Бурятия | C14: текущие точки | H14: новые точки
B15: Великий Новгород | C15: текущие точки | H15: новые точки
... B18: Волгоград | C18: текущие точки | H18: новые точки
B19: Вологда | C19: текущие точки
B20: Воронеж | C20: текущие точки
B21: Дагестан | C21: текущие точки
B22: Донецк | C22: текущие точки
B23: Екатеринбург | C23: текущие точки
B24: Иваново | C24: текущие точки
B25: Ингушетия | C25: текущие точки
B26: Иркутск | C26: текущие точки
B27: Кабардино-Балкария | C27: текущие точки
B28: Калининград | C28: текущие точки
B29: Калмыкия | C29: текущие точки
B30: Калуга | C30: текущие точки
... B91: Новый регион | C91: текущие точки

Sheet спр
A1: старое наименование | B1: новое наименование
A2: Линия бизнеса | B2: Линия бизнеса (форма)
A3: Гибкий курс | B3: ГК
A4: НП | B4: НП
A5: НСЖ | B5: НСЖ
A6: НСЖ с Кэшбеком | B6: НСЖ_КБ
A7: Групп. пенсия | B7: Групп.пенсия
A8: Индив. пенсия | B8: Индив.пенсия
A9: ИСЖ (СиВ) | B9: ИСЖ_СИВ
A10: НСЖ (СиВ) | B10: НСЖ_СИВ
A11: ИСЖ (Уралсиб) | B11: ИСЖ_Уралсиб
A12: НСЖ (Уралсиб) | B12: НСЖ_Уралсиб
... A24: Прочее (Уралсиб) | B24: Прочее_Уралсиб

Sheet ЛБ
E1: 1. Выбираем Портфель (вып список) - > 2. выбираем Линию бизнеса (вып.список) - 3. Выбираем продукт (вып список)
B2: Справочник продуктов | J2: Портфели - ЛБ (для выбора в форме) | P2: Доп аналитики (для выбора в форме
B3: Продукт | C3: Линия бизнеса (форма) | D3: Портфель | E3: L/NL | H3: Портфель | J3: Новый | K3: СКБСЖ | L3: Уралсиб | P3: Новый бизнес/ Пролонгация | R3: Периодичность
B4: Гибкий курс | C4: ГК | D4: Новый | E4: Лайф | H4: Новый | J4: ГК | K4: Групп.пенсия | L4: ИСЖ_Уралсиб | P4: Пролонгация | R4: Единовременная
B5: НП | C5: НП | D5: Новый | E5: Лайф | H5: СКБСЖ | J5: НП | K5: Индив.пенсия | L5: НСЖ_Уралсиб | P5: Новый | R5: Регулярная
B6: Будущее под ключ | C6: НСЖ_новый | D6: Новый | E6: Лайф | H6: Уралсиб | J6: НСЖ_новый | K6: НСЖ | L6: КСЖ_Уралсиб
B7: НСЖ с Кэшбеком | C7: НСЖ_КБ | D7: Новый | E7: Лайф | J7: НСЖ_КБ | K7: НСЖ_СИВ | L7: Прочее_Уралсиб
B8: Групп. пенсия | C8: Групп.пенсия | D8: СКБСЖ | E8: Лайф | K8: ИСЖ_СИВ
B9: Индив Пенсия | C9: Индив.пенсия | D9: СКБСЖ | E9: Лайф | K9: ДМС
B10: Прочее (СИВ) | C10: ИСЖ_СИВ | D10: СКБСЖ | E10: Лайф | K10: ДМС_СИВ
B11: Дело жизни | C11: НСЖ | D11: СКБСЖ | E11: Лайф | K11: КорпЖ
B12: Детский капитал | C12: НСЖ | D12: СКБСЖ | E12: Лайф | K12: КорпНС
B13: Классика+ | C13: НСЖ | D13: СКБСЖ | E13: Лайф | K13: КСЖ
B14: Курс жизни Про | C14: НСЖ | D14: СКБСЖ | E14: Лайф | K14: КСЖ_СИВ
B15: Максимальная выгода | C15: НСЖ | D15: СКБСЖ | E15: Лайф | K15: НС
B16: Прочее (СКБЖ) | C16: НСЖ | D16: СКБСЖ | E16: Лайф | K16: НС_СИВ
B17: Юниор+ | C17: НСЖ | D17: СКБСЖ | E17: Лайф | K17: НСЖ_СИВ_ДМС
B18: Citi Comfort | C18: НСЖ_СИВ | D18: СКБСЖ | E18: Лайф | K18: НСЖ_СИВ_НС
B19: Citi Health | C19: НСЖ_СИВ | D19: СКБСЖ | E19: Лайф
B20: Citi Kids | C20: НСЖ_СИВ | D20: СКБСЖ | E20: Лайф | I20: ЛБ - Продукт для выбора в форме
B21: Citi Premium | C21: НСЖ_СИВ | D21: СКБСЖ | E21: Лайф | I21: ГК | J21: НП | K21: НСЖ_новый | L21: НСЖ_КБ | M21: Групп.пенсия | N21: Индив.пенсия | O21: НСЖ | P21: НСЖ_СИВ | Q21: ИСЖ_СИВ | R21: ДМС | S21: ДМС_СИВ | T21: КорпЖ | U21: КорпНС | V21: КСЖ | W21: КСЖ_СИВ | X21: НС | Y21: НС_СИВ | Z21: НСЖ_СИВ_ДМС | AA21: НСЖ_СИВ_НС | AB21: ИСЖ_Уралсиб | AC21: НСЖ_Уралсиб | AD21: КСЖ_Уралсиб | AE21: Прочее_Уралсиб
B22: Прочее (СИВ) | C22: НСЖ_СИВ | D22: СКБСЖ | E22: Лайф | I22: Гибкий курс | J22: НП | K22: Будущее под ключ | L22: НСЖ с Кэшбеком | M22: Групп. пенсия | N22: Индив Пенсия | O22: Дело жизни | P22: Citi Comfort | Q22: Прочее (СИВ) | R22: ДМС | S22: Прочее (СИВ) | T22: КорпЖ | U22: КорпНС | V22: КСЖ | W22: Прочее (СИВ) | X22: Дело жизни | Y22: Прочее (СИВ) | Z22: Citi Comfort | AA22: Citi Comfort | AB22: Верное решение | AC22: Легкий старт | AD22: КСЖ (Уралсиб) | AE22: Прочее (Уралсиб)
B23: Сила процента | C23: НСЖ_СИВ | D23: СКБСЖ | E23: Лайф | O23: Детский капитал | P23: Citi Health | X23: НС | Z23: Citi Health | AA23: Citi Health | AC23: Прочее (Уралсиб) | AD23: Прочее (Уралсиб)
B24: Стабильный курс | C24: НСЖ_СИВ | D24: СКБСЖ | E24: Лайф | O24: Классика+ | P24: Citi Kids | Z24: Citi Kids | AA24: Citi Kids | AC24: Стабильный доход
B25: Верное решение | C25: ИСЖ_Уралсиб | D25: Уралсиб | E25: Лайф | O25: Курс жизни Про | P25: Citi Premium | Z25: Citi Premium | AA25: Citi Premium
B26: Легкий старт | C26: НСЖ_Уралсиб | D26: Уралсиб | E26: Лайф | O26: Максимальная выгода | P26: Прочее (СИВ) | Z26: Прочее (СИВ) | AA26: Прочее (СИВ)
B27: Прочее (Уралсиб) | C27: НСЖ_Уралсиб | D27: Уралсиб | E27: Лайф | O27: Прочее (СКБЖ) | P27: Сила процента | Z27: Сила процента | AA27: Сила процента
B28: Стабильный доход | C28: НСЖ_Уралсиб | D28: Уралсиб | E28: Лайф | O28: Юниор+ | P28: Стабильный курс | Z28: Стабильный курс | AA28: Стабильный курс
B29: ДМС | C29: ДМС | D29: СКБСЖ | E29: Нон-лайф
B30: Прочее (СИВ) | C30: ДМС_СИВ | D30: СКБСЖ | E30: Нон-лайф
B31: КорпЖ | C31: КорпЖ | D31: СКБСЖ | E31: Нон-лайф
B32: КорпНС | C32: КорпНС | D32: СКБСЖ | E32: Нон-лайф
B33: КСЖ | C33: КСЖ | D33: СКБСЖ | E33: Нон-лайф
B34: Прочее (СИВ) | C34: КСЖ_СИВ | D34: СКБСЖ | E34: Нон-лайф
B35: Дело жизни | C35: НС | D35: СКБСЖ | E35: Нон-лайф
B36: НС | C36: НС | D36: СКБСЖ | E36: Нон-лайф
B37: Прочее (СИВ) | C37: НС_СИВ | D37: СКБСЖ | E37: Нон-лайф
B38: Citi Comfort | C38: НСЖ_СИВ_ДМС | D38: СКБСЖ | E38: Нон-лайф
B39: Citi Health | C39: НСЖ_СИВ_ДМС | D39: СКБСЖ | E39: Нон-лайф
B40: Citi Kids | C40: НСЖ_СИВ_ДМС | D40: СКБСЖ | E40: Нон-лайф
... B44: Стабильный курс | C44: НСЖ_СИВ_ДМС | D44: СКБСЖ | E44: Нон-лайф
B45: Citi Comfort | C45: НСЖ_СИВ_НС | D45: СКБСЖ | E45: Нон-лайф | H45: Названия строк
B46: Citi Health | C46: НСЖ_СИВ_НС | D46: СКБСЖ | E46: Нон-лайф | H46: ГК
B47: Citi Kids | C47: НСЖ_СИВ_НС | D47: СКБСЖ | E47: Нон-лайф | H47: Гибкий курс
B48: Citi Premium | C48: НСЖ_СИВ_НС | D48: СКБСЖ | E48: Нон-лайф | H48: Групп.пенсия
B49: Прочее (СИВ) | C49: НСЖ_СИВ_НС | D49: СКБСЖ | E49: Нон-лайф | H49: Групп. пенсия
B50: Сила процента | C50: НСЖ_СИВ_НС | D50: СКБСЖ | E50: Нон-лайф | H50: ДМС
B51: Стабильный курс | C51: НСЖ_СИВ_НС | D51: СКБСЖ | E51: Нон-лайф | H51: ДМС
B52: КСЖ (Уралсиб) | C52: КСЖ_Уралсиб | D52: Уралсиб | E52: Нон-лайф | H52: ДМС_СИВ
B53: Прочее (Уралсиб) | C53: КСЖ_Уралсиб | D53: Уралсиб | E53: Нон-лайф | H53: Прочее (СИВ)
B54: Прочее (Уралсиб) | C54: Прочее_Уралсиб | D54: Уралсиб | E54: Нон-лайф | H54: Индив.пенсия
H55: Индив Пенсия
H56: ИСЖ_СИВ
H57: Прочее (СИВ)
H58: ИСЖ_Уралсиб
H59: Верное решение
H60: КорпЖ
H61: КорпЖ
H62: КорпНС
H63: КорпНС
H64: КСЖ
H65: КСЖ
H66: КСЖ_СИВ
... H118: Прочее (Уралсиб)
